<?xml version="1.0" encoding="ISO-8859-1"?>
<DeliveryNotes Version="1.0">
  <DeliveryNote>
    <DeliveryHead DeliveryNoteNo="123456" DeliveryDate="2024-04-24" />
    <Devices>
      <Device>
        <MainDevice ZennerShortDescription="PDC LORA DV 2K OFF.KABELENDE IP68" ZennerMaterialNo="156872" WaterMeterLength="" TempRange="" SubDeviceNr="0" SerialNoFull="" Scenario="" RollerDigits="" RadioTelegramType="" RadioTechnology="LoRa" RadioProtocolMode="LoRa" PulseValue="" PrintedSerialNo="04B6480640110511" PermanentFlow="" PacketType="A" NwkSKey="" NetworkKey="" Manufacturer="" MAC_Address="" LoRaWAN_Version="1.0.1" LoRaDeviceClass="" JoinEUI="04b6480000000000" Item="20" Frequency="" DeviceAddr="" DeviceActivationMode="" DevEUI="04b6480640110511" Cycle="" CustomerMaterialNo="" Connection="" CommandVersion="" AppSKey="" AppKey="5BF3984C31991690FE8180B25527924D" AES_Key="" />
      </Device>
      <Device>
        <MainDevice ZennerShortDescription="PDC LORA DV 2K OFF.KABELENDE IP68" ZennerMaterialNo="156872" WaterMeterLength="" TempRange="" SubDeviceNr="0" SerialNoFull="" Scenario="" RollerDigits="" RadioTelegramType="" RadioTechnology="LoRa" RadioProtocolMode="LoRa" PulseValue="" PrintedSerialNo="04B6480640110512" PermanentFlow="" PacketType="A" NwkSKey="" NetworkKey="" Manufacturer="" MAC_Address="" LoRaWAN_Version="1.0.1" LoRaDeviceClass="" JoinEUI="04b6480000000000" Item="20" Frequency="" DeviceAddr="" DeviceActivationMode="" DevEUI="04b6480640110512" Cycle="" CustomerMaterialNo="" Connection="" CommandVersion="" AppSKey="" AppKey="F81B946ED237D024FAC848C6DB095EC8" AES_Key="" />
      </Device>
      <Device>
        <MainDevice ZennerShortDescription="PDC LORA DV 2K OFF.KABELENDE IP68" ZennerMaterialNo="156872" WaterMeterLength="" TempRange="" SubDeviceNr="0" SerialNoFull="" Scenario="" RollerDigits="" RadioTelegramType="" RadioTechnology="LoRa" RadioProtocolMode="LoRa" PulseValue="" PrintedSerialNo="04B6480640110513" PermanentFlow="" PacketType="A" NwkSKey="" NetworkKey="" Manufacturer="" MAC_Address="" LoRaWAN_Version="1.0.1" LoRaDeviceClass="" JoinEUI="04b6480000000000" Item="20" Frequency="" DeviceAddr="" DeviceActivationMode="" DevEUI="04b6480640110513" Cycle="" CustomerMaterialNo="" Connection="" CommandVersion="" AppSKey="" AppKey="004A3E771E91A2AEFB3BFABFC66A7414" AES_Key="" />
      </Device>
      <Device>
        <MainDevice ZennerShortDescription="PDC LORA DV 2K OFF.KABELENDE IP68" ZennerMaterialNo="156872" WaterMeterLength="" TempRange="" SubDeviceNr="0" SerialNoFull="" Scenario="" RollerDigits="" RadioTelegramType="" RadioTechnology="LoRa" RadioProtocolMode="LoRa" PulseValue="" PrintedSerialNo="04B6480640110514" PermanentFlow="" PacketType="A" NwkSKey="" NetworkKey="" Manufacturer="" MAC_Address="" LoRaWAN_Version="1.0.1" LoRaDeviceClass="" JoinEUI="04b6480000000000" Item="20" Frequency="" DeviceAddr="" DeviceActivationMode="" DevEUI="04b6480640110514" Cycle="" CustomerMaterialNo="" Connection="" CommandVersion="" AppSKey="" AppKey="6FD774CA17B56B71B9B67A0996692233" AES_Key="" />
      </Device>
      <Device>
        <MainDevice ZennerShortDescription="PDC LORA DV 2K OFF.KABELENDE IP68" ZennerMaterialNo="156872" WaterMeterLength="" TempRange="" SubDeviceNr="0" SerialNoFull="" Scenario="" RollerDigits="" RadioTelegramType="" RadioTechnology="LoRa" RadioProtocolMode="LoRa" PulseValue="" PrintedSerialNo="04B6480640110515" PermanentFlow="" PacketType="A" NwkSKey="" NetworkKey="" Manufacturer="" MAC_Address="" LoRaWAN_Version="1.0.1" LoRaDeviceClass="" JoinEUI="04b6480000000000" Item="20" Frequency="" DeviceAddr="" DeviceActivationMode="" DevEUI="04b6480640110515" Cycle="" CustomerMaterialNo="" Connection="" CommandVersion="" AppSKey="" AppKey="C93E4BFD5B28AB0F280C33E83A4EC079" AES_Key="" />
      </Device>
    </Devices>
  </DeliveryNote>
</DeliveryNotes>