<?xml version="1.0" encoding="ISO-8859-1"?>
<DeliveryNotes Version="1.0">
  <DeliveryNote>
    <DeliveryHead DeliveryNoteNo="123456" DeliveryDate="2024-04-24" />
    <Devices>
      <Device>
        <MainDevice ZennerShortDescription="MNK-N 4-190-3/4 R80H40V CU 10L" ZennerMaterialNo="140161" WaterMeterLength="" TempRange="" SubDeviceNr="0" SerialNoFull="" Scenario="" RollerDigits="" RadioTelegramType="" RadioTechnology="" RadioProtocolMode="" PulseValue="10 Ltr/I" PrintedSerialNo="8ZRI2417429813" PermanentFlow="" PacketType="" NwkSKey="" NetworkKey="" Manufacturer="" MAC_Address="" LoRaWAN_Version="" LoRaDeviceClass="" JoinEUI="" Item="20" Frequency="" DeviceAddr="" DeviceActivationMode="" DevEUI="" Cycle="" CustomerMaterialNo="" Connection="G1B / DN 20" CommandVersion="" AppSKey="" AppKey="" AES_Key="" />
      </Device>
      <Device>
        <MainDevice ZennerShortDescription="MNK-N 4-190-3/4 R80H40V CU 10L" ZennerMaterialNo="140161" WaterMeterLength="" TempRange="" SubDeviceNr="0" SerialNoFull="" Scenario="" RollerDigits="" RadioTelegramType="" RadioTechnology="" RadioProtocolMode="" PulseValue="10 Ltr/I" PrintedSerialNo="8ZRI2417429814" PermanentFlow="" PacketType="" NwkSKey="" NetworkKey="" Manufacturer="" MAC_Address="" LoRaWAN_Version="" LoRaDeviceClass="" JoinEUI="" Item="20" Frequency="" DeviceAddr="" DeviceActivationMode="" DevEUI="" Cycle="" CustomerMaterialNo="" Connection="G1B / DN 20" CommandVersion="" AppSKey="" AppKey="" AES_Key="" />
      </Device>
      <Device>
        <MainDevice ZennerShortDescription="MNK-N 4-190-3/4 R80H40V CU 10L" ZennerMaterialNo="140161" WaterMeterLength="" TempRange="" SubDeviceNr="0" SerialNoFull="" Scenario="" RollerDigits="" RadioTelegramType="" RadioTechnology="" RadioProtocolMode="" PulseValue="10 Ltr/I" PrintedSerialNo="8ZRI2417429815" PermanentFlow="" PacketType="" NwkSKey="" NetworkKey="" Manufacturer="" MAC_Address="" LoRaWAN_Version="" LoRaDeviceClass="" JoinEUI="" Item="20" Frequency="" DeviceAddr="" DeviceActivationMode="" DevEUI="" Cycle="" CustomerMaterialNo="" Connection="G1B / DN 20" CommandVersion="" AppSKey="" AppKey="" AES_Key="" />
      </Device>
      <Device>
        <MainDevice ZennerShortDescription="MNK-N 4-190-3/4 R80H40V CU 10L" ZennerMaterialNo="140161" WaterMeterLength="" TempRange="" SubDeviceNr="0" SerialNoFull="" Scenario="" RollerDigits="" RadioTelegramType="" RadioTechnology="" RadioProtocolMode="" PulseValue="10 Ltr/I" PrintedSerialNo="8ZRI2417429816" PermanentFlow="" PacketType="" NwkSKey="" NetworkKey="" Manufacturer="" MAC_Address="" LoRaWAN_Version="" LoRaDeviceClass="" JoinEUI="" Item="20" Frequency="" DeviceAddr="" DeviceActivationMode="" DevEUI="" Cycle="" CustomerMaterialNo="" Connection="G1B / DN 20" CommandVersion="" AppSKey="" AppKey="" AES_Key="" />
      </Device>
      <Device>
        <MainDevice ZennerShortDescription="MNK-N 4-190-3/4 R80H40V CU 10L" ZennerMaterialNo="140161" WaterMeterLength="" TempRange="" SubDeviceNr="0" SerialNoFull="" Scenario="" RollerDigits="" RadioTelegramType="" RadioTechnology="" RadioProtocolMode="" PulseValue="10 Ltr/I" PrintedSerialNo="8ZRI2417429817" PermanentFlow="" PacketType="" NwkSKey="" NetworkKey="" Manufacturer="" MAC_Address="" LoRaWAN_Version="" LoRaDeviceClass="" JoinEUI="" Item="20" Frequency="" DeviceAddr="" DeviceActivationMode="" DevEUI="" Cycle="" CustomerMaterialNo="" Connection="G1B / DN 20" CommandVersion="" AppSKey="" AppKey="" AES_Key="" />
      </Device>
      <Device>
        <MainDevice ZennerShortDescription="MNK-N 4-190-3/4 R80H40V CU 10L" ZennerMaterialNo="140161" WaterMeterLength="" TempRange="" SubDeviceNr="0" SerialNoFull="" Scenario="" RollerDigits="" RadioTelegramType="" RadioTechnology="" RadioProtocolMode="" PulseValue="10 Ltr/I" PrintedSerialNo="8ZRI2417429818" PermanentFlow="" PacketType="" NwkSKey="" NetworkKey="" Manufacturer="" MAC_Address="" LoRaWAN_Version="" LoRaDeviceClass="" JoinEUI="" Item="20" Frequency="" DeviceAddr="" DeviceActivationMode="" DevEUI="" Cycle="" CustomerMaterialNo="" Connection="G1B / DN 20" CommandVersion="" AppSKey="" AppKey="" AES_Key="" />
      </Device>
      <Device>
        <MainDevice ZennerShortDescription="MNK-N 4-190-3/4 R80H40V CU 10L" ZennerMaterialNo="140161" WaterMeterLength="" TempRange="" SubDeviceNr="0" SerialNoFull="" Scenario="" RollerDigits="" RadioTelegramType="" RadioTechnology="" RadioProtocolMode="" PulseValue="10 Ltr/I" PrintedSerialNo="8ZRI2417429819" PermanentFlow="" PacketType="" NwkSKey="" NetworkKey="" Manufacturer="" MAC_Address="" LoRaWAN_Version="" LoRaDeviceClass="" JoinEUI="" Item="20" Frequency="" DeviceAddr="" DeviceActivationMode="" DevEUI="" Cycle="" CustomerMaterialNo="" Connection="G1B / DN 20" CommandVersion="" AppSKey="" AppKey="" AES_Key="" />
      </Device>
      <Device>
        <MainDevice ZennerShortDescription="MNK-N 4-190-3/4 R80H40V CU 10L" ZennerMaterialNo="140161" WaterMeterLength="" TempRange="" SubDeviceNr="0" SerialNoFull="" Scenario="" RollerDigits="" RadioTelegramType="" RadioTechnology="" RadioProtocolMode="" PulseValue="10 Ltr/I" PrintedSerialNo="8ZRI2417429820" PermanentFlow="" PacketType="" NwkSKey="" NetworkKey="" Manufacturer="" MAC_Address="" LoRaWAN_Version="" LoRaDeviceClass="" JoinEUI="" Item="20" Frequency="" DeviceAddr="" DeviceActivationMode="" DevEUI="" Cycle="" CustomerMaterialNo="" Connection="G1B / DN 20" CommandVersion="" AppSKey="" AppKey="" AES_Key="" />
      </Device>
      <Device>
        <MainDevice ZennerShortDescription="MNK-N 4-190-3/4 R80H40V CU 10L" ZennerMaterialNo="140161" WaterMeterLength="" TempRange="" SubDeviceNr="0" SerialNoFull="" Scenario="" RollerDigits="" RadioTelegramType="" RadioTechnology="" RadioProtocolMode="" PulseValue="10 Ltr/I" PrintedSerialNo="8ZRI2417429821" PermanentFlow="" PacketType="" NwkSKey="" NetworkKey="" Manufacturer="" MAC_Address="" LoRaWAN_Version="" LoRaDeviceClass="" JoinEUI="" Item="20" Frequency="" DeviceAddr="" DeviceActivationMode="" DevEUI="" Cycle="" CustomerMaterialNo="" Connection="G1B / DN 20" CommandVersion="" AppSKey="" AppKey="" AES_Key="" />
      </Device>
      <Device>
        <MainDevice ZennerShortDescription="MNK-N 4-190-3/4 R80H40V CU 10L" ZennerMaterialNo="140161" WaterMeterLength="" TempRange="" SubDeviceNr="0" SerialNoFull="" Scenario="" RollerDigits="" RadioTelegramType="" RadioTechnology="" RadioProtocolMode="" PulseValue="10 Ltr/I" PrintedSerialNo="8ZRI2417429822" PermanentFlow="" PacketType="" NwkSKey="" NetworkKey="" Manufacturer="" MAC_Address="" LoRaWAN_Version="" LoRaDeviceClass="" JoinEUI="" Item="20" Frequency="" DeviceAddr="" DeviceActivationMode="" DevEUI="" Cycle="" CustomerMaterialNo="" Connection="G1B / DN 20" CommandVersion="" AppSKey="" AppKey="" AES_Key="" />
      </Device>
      <Device>
        <MainDevice ZennerShortDescription="MNK-N 4-190-3/4 R80H40V CU 10L" ZennerMaterialNo="140161" WaterMeterLength="" TempRange="" SubDeviceNr="0" SerialNoFull="" Scenario="" RollerDigits="" RadioTelegramType="" RadioTechnology="" RadioProtocolMode="" PulseValue="10 Ltr/I" PrintedSerialNo="8ZRI2417429823" PermanentFlow="" PacketType="" NwkSKey="" NetworkKey="" Manufacturer="" MAC_Address="" LoRaWAN_Version="" LoRaDeviceClass="" JoinEUI="" Item="20" Frequency="" DeviceAddr="" DeviceActivationMode="" DevEUI="" Cycle="" CustomerMaterialNo="" Connection="G1B / DN 20" CommandVersion="" AppSKey="" AppKey="" AES_Key="" />
      </Device>
      <Device>
        <MainDevice ZennerShortDescription="MNK-N 4-190-3/4 R80H40V CU 10L" ZennerMaterialNo="140161" WaterMeterLength="" TempRange="" SubDeviceNr="0" SerialNoFull="" Scenario="" RollerDigits="" RadioTelegramType="" RadioTechnology="" RadioProtocolMode="" PulseValue="10 Ltr/I" PrintedSerialNo="8ZRI2417429824" PermanentFlow="" PacketType="" NwkSKey="" NetworkKey="" Manufacturer="" MAC_Address="" LoRaWAN_Version="" LoRaDeviceClass="" JoinEUI="" Item="20" Frequency="" DeviceAddr="" DeviceActivationMode="" DevEUI="" Cycle="" CustomerMaterialNo="" Connection="G1B / DN 20" CommandVersion="" AppSKey="" AppKey="" AES_Key="" />
      </Device>
      <Device>
        <MainDevice ZennerShortDescription="MNK-N 4-190-3/4 R80H40V CU 10L" ZennerMaterialNo="140161" WaterMeterLength="" TempRange="" SubDeviceNr="0" SerialNoFull="" Scenario="" RollerDigits="" RadioTelegramType="" RadioTechnology="" RadioProtocolMode="" PulseValue="10 Ltr/I" PrintedSerialNo="8ZRI2417429825" PermanentFlow="" PacketType="" NwkSKey="" NetworkKey="" Manufacturer="" MAC_Address="" LoRaWAN_Version="" LoRaDeviceClass="" JoinEUI="" Item="20" Frequency="" DeviceAddr="" DeviceActivationMode="" DevEUI="" Cycle="" CustomerMaterialNo="" Connection="G1B / DN 20" CommandVersion="" AppSKey="" AppKey="" AES_Key="" />
      </Device>
      <Device>
        <MainDevice ZennerShortDescription="MNK-N 4-190-3/4 R80H40V CU 10L" ZennerMaterialNo="140161" WaterMeterLength="" TempRange="" SubDeviceNr="0" SerialNoFull="" Scenario="" RollerDigits="" RadioTelegramType="" RadioTechnology="" RadioProtocolMode="" PulseValue="10 Ltr/I" PrintedSerialNo="8ZRI2417429826" PermanentFlow="" PacketType="" NwkSKey="" NetworkKey="" Manufacturer="" MAC_Address="" LoRaWAN_Version="" LoRaDeviceClass="" JoinEUI="" Item="20" Frequency="" DeviceAddr="" DeviceActivationMode="" DevEUI="" Cycle="" CustomerMaterialNo="" Connection="G1B / DN 20" CommandVersion="" AppSKey="" AppKey="" AES_Key="" />
      </Device>
      <Device>
        <MainDevice ZennerShortDescription="MNK-N 4-190-3/4 R80H40V CU 10L" ZennerMaterialNo="140161" WaterMeterLength="" TempRange="" SubDeviceNr="0" SerialNoFull="" Scenario="" RollerDigits="" RadioTelegramType="" RadioTechnology="" RadioProtocolMode="" PulseValue="10 Ltr/I" PrintedSerialNo="8ZRI2417429827" PermanentFlow="" PacketType="" NwkSKey="" NetworkKey="" Manufacturer="" MAC_Address="" LoRaWAN_Version="" LoRaDeviceClass="" JoinEUI="" Item="20" Frequency="" DeviceAddr="" DeviceActivationMode="" DevEUI="" Cycle="" CustomerMaterialNo="" Connection="G1B / DN 20" CommandVersion="" AppSKey="" AppKey="" AES_Key="" />
      </Device>
      <Device>
        <MainDevice ZennerShortDescription="MNK-N 4-190-3/4 R80H40V CU 10L" ZennerMaterialNo="140161" WaterMeterLength="" TempRange="" SubDeviceNr="0" SerialNoFull="" Scenario="" RollerDigits="" RadioTelegramType="" RadioTechnology="" RadioProtocolMode="" PulseValue="10 Ltr/I" PrintedSerialNo="8ZRI2417429828" PermanentFlow="" PacketType="" NwkSKey="" NetworkKey="" Manufacturer="" MAC_Address="" LoRaWAN_Version="" LoRaDeviceClass="" JoinEUI="" Item="20" Frequency="" DeviceAddr="" DeviceActivationMode="" DevEUI="" Cycle="" CustomerMaterialNo="" Connection="G1B / DN 20" CommandVersion="" AppSKey="" AppKey="" AES_Key="" />
      </Device>
      <Device>
        <MainDevice ZennerShortDescription="MNK-N 4-190-3/4 R80H40V CU 10L" ZennerMaterialNo="140161" WaterMeterLength="" TempRange="" SubDeviceNr="0" SerialNoFull="" Scenario="" RollerDigits="" RadioTelegramType="" RadioTechnology="" RadioProtocolMode="" PulseValue="10 Ltr/I" PrintedSerialNo="8ZRI2417429829" PermanentFlow="" PacketType="" NwkSKey="" NetworkKey="" Manufacturer="" MAC_Address="" LoRaWAN_Version="" LoRaDeviceClass="" JoinEUI="" Item="20" Frequency="" DeviceAddr="" DeviceActivationMode="" DevEUI="" Cycle="" CustomerMaterialNo="" Connection="G1B / DN 20" CommandVersion="" AppSKey="" AppKey="" AES_Key="" />
      </Device>
      <Device>
        <MainDevice ZennerShortDescription="MNK-N 4-190-3/4 R80H40V CU 10L" ZennerMaterialNo="140161" WaterMeterLength="" TempRange="" SubDeviceNr="0" SerialNoFull="" Scenario="" RollerDigits="" RadioTelegramType="" RadioTechnology="" RadioProtocolMode="" PulseValue="10 Ltr/I" PrintedSerialNo="8ZRI2417429830" PermanentFlow="" PacketType="" NwkSKey="" NetworkKey="" Manufacturer="" MAC_Address="" LoRaWAN_Version="" LoRaDeviceClass="" JoinEUI="" Item="20" Frequency="" DeviceAddr="" DeviceActivationMode="" DevEUI="" Cycle="" CustomerMaterialNo="" Connection="G1B / DN 20" CommandVersion="" AppSKey="" AppKey="" AES_Key="" />
      </Device>
      <Device>
        <MainDevice ZennerShortDescription="MNK-N 4-190-3/4 R80H40V CU 10L" ZennerMaterialNo="140161" WaterMeterLength="" TempRange="" SubDeviceNr="0" SerialNoFull="" Scenario="" RollerDigits="" RadioTelegramType="" RadioTechnology="" RadioProtocolMode="" PulseValue="10 Ltr/I" PrintedSerialNo="8ZRI2417429831" PermanentFlow="" PacketType="" NwkSKey="" NetworkKey="" Manufacturer="" MAC_Address="" LoRaWAN_Version="" LoRaDeviceClass="" JoinEUI="" Item="20" Frequency="" DeviceAddr="" DeviceActivationMode="" DevEUI="" Cycle="" CustomerMaterialNo="" Connection="G1B / DN 20" CommandVersion="" AppSKey="" AppKey="" AES_Key="" />
      </Device>
      <Device>
        <MainDevice ZennerShortDescription="MNK-N 4-190-3/4 R80H40V CU 10L" ZennerMaterialNo="140161" WaterMeterLength="" TempRange="" SubDeviceNr="0" SerialNoFull="" Scenario="" RollerDigits="" RadioTelegramType="" RadioTechnology="" RadioProtocolMode="" PulseValue="10 Ltr/I" PrintedSerialNo="8ZRI2417429832" PermanentFlow="" PacketType="" NwkSKey="" NetworkKey="" Manufacturer="" MAC_Address="" LoRaWAN_Version="" LoRaDeviceClass="" JoinEUI="" Item="20" Frequency="" DeviceAddr="" DeviceActivationMode="" DevEUI="" Cycle="" CustomerMaterialNo="" Connection="G1B / DN 20" CommandVersion="" AppSKey="" AppKey="" AES_Key="" />
      </Device>
      <Device>
        <MainDevice ZennerShortDescription="MNK-N 4-190-3/4 R80H40V CU 10L" ZennerMaterialNo="140161" WaterMeterLength="" TempRange="" SubDeviceNr="0" SerialNoFull="" Scenario="" RollerDigits="" RadioTelegramType="" RadioTechnology="" RadioProtocolMode="" PulseValue="10 Ltr/I" PrintedSerialNo="8ZRI2417429833" PermanentFlow="" PacketType="" NwkSKey="" NetworkKey="" Manufacturer="" MAC_Address="" LoRaWAN_Version="" LoRaDeviceClass="" JoinEUI="" Item="20" Frequency="" DeviceAddr="" DeviceActivationMode="" DevEUI="" Cycle="" CustomerMaterialNo="" Connection="G1B / DN 20" CommandVersion="" AppSKey="" AppKey="" AES_Key="" />
      </Device>
      <Device>
        <MainDevice ZennerShortDescription="MNK-N 4-190-3/4 R80H40V CU 10L" ZennerMaterialNo="140161" WaterMeterLength="" TempRange="" SubDeviceNr="0" SerialNoFull="" Scenario="" RollerDigits="" RadioTelegramType="" RadioTechnology="" RadioProtocolMode="" PulseValue="10 Ltr/I" PrintedSerialNo="8ZRI2417429834" PermanentFlow="" PacketType="" NwkSKey="" NetworkKey="" Manufacturer="" MAC_Address="" LoRaWAN_Version="" LoRaDeviceClass="" JoinEUI="" Item="20" Frequency="" DeviceAddr="" DeviceActivationMode="" DevEUI="" Cycle="" CustomerMaterialNo="" Connection="G1B / DN 20" CommandVersion="" AppSKey="" AppKey="" AES_Key="" />
      </Device>
      <Device>
        <MainDevice ZennerShortDescription="MNK-N 4-190-3/4 R80H40V CU 10L" ZennerMaterialNo="140161" WaterMeterLength="" TempRange="" SubDeviceNr="0" SerialNoFull="" Scenario="" RollerDigits="" RadioTelegramType="" RadioTechnology="" RadioProtocolMode="" PulseValue="10 Ltr/I" PrintedSerialNo="8ZRI2417429835" PermanentFlow="" PacketType="" NwkSKey="" NetworkKey="" Manufacturer="" MAC_Address="" LoRaWAN_Version="" LoRaDeviceClass="" JoinEUI="" Item="20" Frequency="" DeviceAddr="" DeviceActivationMode="" DevEUI="" Cycle="" CustomerMaterialNo="" Connection="G1B / DN 20" CommandVersion="" AppSKey="" AppKey="" AES_Key="" />
      </Device>
      <Device>
        <MainDevice ZennerShortDescription="MNK-N 4-190-3/4 R80H40V CU 10L" ZennerMaterialNo="140161" WaterMeterLength="" TempRange="" SubDeviceNr="0" SerialNoFull="" Scenario="" RollerDigits="" RadioTelegramType="" RadioTechnology="" RadioProtocolMode="" PulseValue="10 Ltr/I" PrintedSerialNo="8ZRI2417429836" PermanentFlow="" PacketType="" NwkSKey="" NetworkKey="" Manufacturer="" MAC_Address="" LoRaWAN_Version="" LoRaDeviceClass="" JoinEUI="" Item="20" Frequency="" DeviceAddr="" DeviceActivationMode="" DevEUI="" Cycle="" CustomerMaterialNo="" Connection="G1B / DN 20" CommandVersion="" AppSKey="" AppKey="" AES_Key="" />
      </Device>
      <Device>
        <MainDevice ZennerShortDescription="MNK-N 4-190-3/4 R80H40V CU 10L" ZennerMaterialNo="140161" WaterMeterLength="" TempRange="" SubDeviceNr="0" SerialNoFull="" Scenario="" RollerDigits="" RadioTelegramType="" RadioTechnology="" RadioProtocolMode="" PulseValue="10 Ltr/I" PrintedSerialNo="8ZRI2417429837" PermanentFlow="" PacketType="" NwkSKey="" NetworkKey="" Manufacturer="" MAC_Address="" LoRaWAN_Version="" LoRaDeviceClass="" JoinEUI="" Item="20" Frequency="" DeviceAddr="" DeviceActivationMode="" DevEUI="" Cycle="" CustomerMaterialNo="" Connection="G1B / DN 20" CommandVersion="" AppSKey="" AppKey="" AES_Key="" />
      </Device>
      <Device>
        <MainDevice ZennerShortDescription="MNK-N 4-190-3/4 R80H40V CU 10L" ZennerMaterialNo="140161" WaterMeterLength="" TempRange="" SubDeviceNr="0" SerialNoFull="" Scenario="" RollerDigits="" RadioTelegramType="" RadioTechnology="" RadioProtocolMode="" PulseValue="10 Ltr/I" PrintedSerialNo="8ZRI2417429838" PermanentFlow="" PacketType="" NwkSKey="" NetworkKey="" Manufacturer="" MAC_Address="" LoRaWAN_Version="" LoRaDeviceClass="" JoinEUI="" Item="20" Frequency="" DeviceAddr="" DeviceActivationMode="" DevEUI="" Cycle="" CustomerMaterialNo="" Connection="G1B / DN 20" CommandVersion="" AppSKey="" AppKey="" AES_Key="" />
      </Device>
      <Device>
        <MainDevice ZennerShortDescription="MNK-N 4-190-3/4 R80H40V CU 10L" ZennerMaterialNo="140161" WaterMeterLength="" TempRange="" SubDeviceNr="0" SerialNoFull="" Scenario="" RollerDigits="" RadioTelegramType="" RadioTechnology="" RadioProtocolMode="" PulseValue="10 Ltr/I" PrintedSerialNo="8ZRI2417429839" PermanentFlow="" PacketType="" NwkSKey="" NetworkKey="" Manufacturer="" MAC_Address="" LoRaWAN_Version="" LoRaDeviceClass="" JoinEUI="" Item="20" Frequency="" DeviceAddr="" DeviceActivationMode="" DevEUI="" Cycle="" CustomerMaterialNo="" Connection="G1B / DN 20" CommandVersion="" AppSKey="" AppKey="" AES_Key="" />
      </Device>
      <Device>
        <MainDevice ZennerShortDescription="MNK-N 4-190-3/4 R80H40V CU 10L" ZennerMaterialNo="140161" WaterMeterLength="" TempRange="" SubDeviceNr="0" SerialNoFull="" Scenario="" RollerDigits="" RadioTelegramType="" RadioTechnology="" RadioProtocolMode="" PulseValue="10 Ltr/I" PrintedSerialNo="8ZRI2417429840" PermanentFlow="" PacketType="" NwkSKey="" NetworkKey="" Manufacturer="" MAC_Address="" LoRaWAN_Version="" LoRaDeviceClass="" JoinEUI="" Item="20" Frequency="" DeviceAddr="" DeviceActivationMode="" DevEUI="" Cycle="" CustomerMaterialNo="" Connection="G1B / DN 20" CommandVersion="" AppSKey="" AppKey="" AES_Key="" />
      </Device>
      <Device>
        <MainDevice ZennerShortDescription="MNK-N 4-190-3/4 R80H40V CU 10L" ZennerMaterialNo="140161" WaterMeterLength="" TempRange="" SubDeviceNr="0" SerialNoFull="" Scenario="" RollerDigits="" RadioTelegramType="" RadioTechnology="" RadioProtocolMode="" PulseValue="10 Ltr/I" PrintedSerialNo="8ZRI2417429841" PermanentFlow="" PacketType="" NwkSKey="" NetworkKey="" Manufacturer="" MAC_Address="" LoRaWAN_Version="" LoRaDeviceClass="" JoinEUI="" Item="20" Frequency="" DeviceAddr="" DeviceActivationMode="" DevEUI="" Cycle="" CustomerMaterialNo="" Connection="G1B / DN 20" CommandVersion="" AppSKey="" AppKey="" AES_Key="" />
      </Device>
      <Device>
        <MainDevice ZennerShortDescription="MNK-N 4-190-3/4 R80H40V CU 10L" ZennerMaterialNo="140161" WaterMeterLength="" TempRange="" SubDeviceNr="0" SerialNoFull="" Scenario="" RollerDigits="" RadioTelegramType="" RadioTechnology="" RadioProtocolMode="" PulseValue="10 Ltr/I" PrintedSerialNo="8ZRI2417429842" PermanentFlow="" PacketType="" NwkSKey="" NetworkKey="" Manufacturer="" MAC_Address="" LoRaWAN_Version="" LoRaDeviceClass="" JoinEUI="" Item="20" Frequency="" DeviceAddr="" DeviceActivationMode="" DevEUI="" Cycle="" CustomerMaterialNo="" Connection="G1B / DN 20" CommandVersion="" AppSKey="" AppKey="" AES_Key="" />
      </Device>
      <Device>
        <MainDevice ZennerShortDescription="MNK-N 4-190-3/4 R80H40V CU 10L" ZennerMaterialNo="140161" WaterMeterLength="" TempRange="" SubDeviceNr="0" SerialNoFull="" Scenario="" RollerDigits="" RadioTelegramType="" RadioTechnology="" RadioProtocolMode="" PulseValue="10 Ltr/I" PrintedSerialNo="8ZRI2417429843" PermanentFlow="" PacketType="" NwkSKey="" NetworkKey="" Manufacturer="" MAC_Address="" LoRaWAN_Version="" LoRaDeviceClass="" JoinEUI="" Item="20" Frequency="" DeviceAddr="" DeviceActivationMode="" DevEUI="" Cycle="" CustomerMaterialNo="" Connection="G1B / DN 20" CommandVersion="" AppSKey="" AppKey="" AES_Key="" />
      </Device>
      <Device>
        <MainDevice ZennerShortDescription="MNK-N 4-190-3/4 R80H40V CU 10L" ZennerMaterialNo="140161" WaterMeterLength="" TempRange="" SubDeviceNr="0" SerialNoFull="" Scenario="" RollerDigits="" RadioTelegramType="" RadioTechnology="" RadioProtocolMode="" PulseValue="10 Ltr/I" PrintedSerialNo="8ZRI2417429844" PermanentFlow="" PacketType="" NwkSKey="" NetworkKey="" Manufacturer="" MAC_Address="" LoRaWAN_Version="" LoRaDeviceClass="" JoinEUI="" Item="20" Frequency="" DeviceAddr="" DeviceActivationMode="" DevEUI="" Cycle="" CustomerMaterialNo="" Connection="G1B / DN 20" CommandVersion="" AppSKey="" AppKey="" AES_Key="" />
      </Device>
      <Device>
        <MainDevice ZennerShortDescription="MNK-N 4-190-3/4 R80H40V CU 10L" ZennerMaterialNo="140161" WaterMeterLength="" TempRange="" SubDeviceNr="0" SerialNoFull="" Scenario="" RollerDigits="" RadioTelegramType="" RadioTechnology="" RadioProtocolMode="" PulseValue="10 Ltr/I" PrintedSerialNo="8ZRI2417429845" PermanentFlow="" PacketType="" NwkSKey="" NetworkKey="" Manufacturer="" MAC_Address="" LoRaWAN_Version="" LoRaDeviceClass="" JoinEUI="" Item="20" Frequency="" DeviceAddr="" DeviceActivationMode="" DevEUI="" Cycle="" CustomerMaterialNo="" Connection="G1B / DN 20" CommandVersion="" AppSKey="" AppKey="" AES_Key="" />
      </Device>
      <Device>
        <MainDevice ZennerShortDescription="MNK-N 4-190-3/4 R80H40V CU 10L" ZennerMaterialNo="140161" WaterMeterLength="" TempRange="" SubDeviceNr="0" SerialNoFull="" Scenario="" RollerDigits="" RadioTelegramType="" RadioTechnology="" RadioProtocolMode="" PulseValue="10 Ltr/I" PrintedSerialNo="8ZRI2417429846" PermanentFlow="" PacketType="" NwkSKey="" NetworkKey="" Manufacturer="" MAC_Address="" LoRaWAN_Version="" LoRaDeviceClass="" JoinEUI="" Item="20" Frequency="" DeviceAddr="" DeviceActivationMode="" DevEUI="" Cycle="" CustomerMaterialNo="" Connection="G1B / DN 20" CommandVersion="" AppSKey="" AppKey="" AES_Key="" />
      </Device>
      <Device>
        <MainDevice ZennerShortDescription="MNK-N 4-190-3/4 R80H40V CU 10L" ZennerMaterialNo="140161" WaterMeterLength="" TempRange="" SubDeviceNr="0" SerialNoFull="" Scenario="" RollerDigits="" RadioTelegramType="" RadioTechnology="" RadioProtocolMode="" PulseValue="10 Ltr/I" PrintedSerialNo="8ZRI2417429847" PermanentFlow="" PacketType="" NwkSKey="" NetworkKey="" Manufacturer="" MAC_Address="" LoRaWAN_Version="" LoRaDeviceClass="" JoinEUI="" Item="20" Frequency="" DeviceAddr="" DeviceActivationMode="" DevEUI="" Cycle="" CustomerMaterialNo="" Connection="G1B / DN 20" CommandVersion="" AppSKey="" AppKey="" AES_Key="" />
      </Device>
      <Device>
        <MainDevice ZennerShortDescription="MNK-N 4-190-3/4 R80H40V CU 10L" ZennerMaterialNo="140161" WaterMeterLength="" TempRange="" SubDeviceNr="0" SerialNoFull="" Scenario="" RollerDigits="" RadioTelegramType="" RadioTechnology="" RadioProtocolMode="" PulseValue="10 Ltr/I" PrintedSerialNo="8ZRI2417429848" PermanentFlow="" PacketType="" NwkSKey="" NetworkKey="" Manufacturer="" MAC_Address="" LoRaWAN_Version="" LoRaDeviceClass="" JoinEUI="" Item="20" Frequency="" DeviceAddr="" DeviceActivationMode="" DevEUI="" Cycle="" CustomerMaterialNo="" Connection="G1B / DN 20" CommandVersion="" AppSKey="" AppKey="" AES_Key="" />
      </Device>
      <Device>
        <MainDevice ZennerShortDescription="MNK-N 4-190-3/4 R80H40V CU 10L" ZennerMaterialNo="140161" WaterMeterLength="" TempRange="" SubDeviceNr="0" SerialNoFull="" Scenario="" RollerDigits="" RadioTelegramType="" RadioTechnology="" RadioProtocolMode="" PulseValue="10 Ltr/I" PrintedSerialNo="8ZRI2417429849" PermanentFlow="" PacketType="" NwkSKey="" NetworkKey="" Manufacturer="" MAC_Address="" LoRaWAN_Version="" LoRaDeviceClass="" JoinEUI="" Item="20" Frequency="" DeviceAddr="" DeviceActivationMode="" DevEUI="" Cycle="" CustomerMaterialNo="" Connection="G1B / DN 20" CommandVersion="" AppSKey="" AppKey="" AES_Key="" />
      </Device>
      <Device>
        <MainDevice ZennerShortDescription="MNK-N 4-190-3/4 R80H40V CU 10L" ZennerMaterialNo="140161" WaterMeterLength="" TempRange="" SubDeviceNr="0" SerialNoFull="" Scenario="" RollerDigits="" RadioTelegramType="" RadioTechnology="" RadioProtocolMode="" PulseValue="10 Ltr/I" PrintedSerialNo="8ZRI2417429850" PermanentFlow="" PacketType="" NwkSKey="" NetworkKey="" Manufacturer="" MAC_Address="" LoRaWAN_Version="" LoRaDeviceClass="" JoinEUI="" Item="20" Frequency="" DeviceAddr="" DeviceActivationMode="" DevEUI="" Cycle="" CustomerMaterialNo="" Connection="G1B / DN 20" CommandVersion="" AppSKey="" AppKey="" AES_Key="" />
      </Device>
      <Device>
        <MainDevice ZennerShortDescription="MNK-N 4-190-3/4 R80H40V CU 10L" ZennerMaterialNo="140161" WaterMeterLength="" TempRange="" SubDeviceNr="0" SerialNoFull="" Scenario="" RollerDigits="" RadioTelegramType="" RadioTechnology="" RadioProtocolMode="" PulseValue="10 Ltr/I" PrintedSerialNo="8ZRI2417429851" PermanentFlow="" PacketType="" NwkSKey="" NetworkKey="" Manufacturer="" MAC_Address="" LoRaWAN_Version="" LoRaDeviceClass="" JoinEUI="" Item="20" Frequency="" DeviceAddr="" DeviceActivationMode="" DevEUI="" Cycle="" CustomerMaterialNo="" Connection="G1B / DN 20" CommandVersion="" AppSKey="" AppKey="" AES_Key="" />
      </Device>
      <Device>
        <MainDevice ZennerShortDescription="MNK-N 4-190-3/4 R80H40V CU 10L" ZennerMaterialNo="140161" WaterMeterLength="" TempRange="" SubDeviceNr="0" SerialNoFull="" Scenario="" RollerDigits="" RadioTelegramType="" RadioTechnology="" RadioProtocolMode="" PulseValue="10 Ltr/I" PrintedSerialNo="8ZRI2417429852" PermanentFlow="" PacketType="" NwkSKey="" NetworkKey="" Manufacturer="" MAC_Address="" LoRaWAN_Version="" LoRaDeviceClass="" JoinEUI="" Item="20" Frequency="" DeviceAddr="" DeviceActivationMode="" DevEUI="" Cycle="" CustomerMaterialNo="" Connection="G1B / DN 20" CommandVersion="" AppSKey="" AppKey="" AES_Key="" />
      </Device>
      <Device>
        <MainDevice ZennerShortDescription="MNK-N 4-190-3/4 R80H40V CU 10L" ZennerMaterialNo="140161" WaterMeterLength="" TempRange="" SubDeviceNr="0" SerialNoFull="" Scenario="" RollerDigits="" RadioTelegramType="" RadioTechnology="" RadioProtocolMode="" PulseValue="10 Ltr/I" PrintedSerialNo="8ZRI2417429853" PermanentFlow="" PacketType="" NwkSKey="" NetworkKey="" Manufacturer="" MAC_Address="" LoRaWAN_Version="" LoRaDeviceClass="" JoinEUI="" Item="20" Frequency="" DeviceAddr="" DeviceActivationMode="" DevEUI="" Cycle="" CustomerMaterialNo="" Connection="G1B / DN 20" CommandVersion="" AppSKey="" AppKey="" AES_Key="" />
      </Device>
      <Device>
        <MainDevice ZennerShortDescription="MNK-N 4-190-3/4 R80H40V CU 10L" ZennerMaterialNo="140161" WaterMeterLength="" TempRange="" SubDeviceNr="0" SerialNoFull="" Scenario="" RollerDigits="" RadioTelegramType="" RadioTechnology="" RadioProtocolMode="" PulseValue="10 Ltr/I" PrintedSerialNo="8ZRI2417429854" PermanentFlow="" PacketType="" NwkSKey="" NetworkKey="" Manufacturer="" MAC_Address="" LoRaWAN_Version="" LoRaDeviceClass="" JoinEUI="" Item="20" Frequency="" DeviceAddr="" DeviceActivationMode="" DevEUI="" Cycle="" CustomerMaterialNo="" Connection="G1B / DN 20" CommandVersion="" AppSKey="" AppKey="" AES_Key="" />
      </Device>
      <Device>
        <MainDevice ZennerShortDescription="MNK-N 4-190-3/4 R80H40V CU 10L" ZennerMaterialNo="140161" WaterMeterLength="" TempRange="" SubDeviceNr="0" SerialNoFull="" Scenario="" RollerDigits="" RadioTelegramType="" RadioTechnology="" RadioProtocolMode="" PulseValue="10 Ltr/I" PrintedSerialNo="8ZRI2417429855" PermanentFlow="" PacketType="" NwkSKey="" NetworkKey="" Manufacturer="" MAC_Address="" LoRaWAN_Version="" LoRaDeviceClass="" JoinEUI="" Item="20" Frequency="" DeviceAddr="" DeviceActivationMode="" DevEUI="" Cycle="" CustomerMaterialNo="" Connection="G1B / DN 20" CommandVersion="" AppSKey="" AppKey="" AES_Key="" />
      </Device>
      <Device>
        <MainDevice ZennerShortDescription="MNK-N 4-190-3/4 R80H40V CU 10L" ZennerMaterialNo="140161" WaterMeterLength="" TempRange="" SubDeviceNr="0" SerialNoFull="" Scenario="" RollerDigits="" RadioTelegramType="" RadioTechnology="" RadioProtocolMode="" PulseValue="10 Ltr/I" PrintedSerialNo="8ZRI2417429856" PermanentFlow="" PacketType="" NwkSKey="" NetworkKey="" Manufacturer="" MAC_Address="" LoRaWAN_Version="" LoRaDeviceClass="" JoinEUI="" Item="20" Frequency="" DeviceAddr="" DeviceActivationMode="" DevEUI="" Cycle="" CustomerMaterialNo="" Connection="G1B / DN 20" CommandVersion="" AppSKey="" AppKey="" AES_Key="" />
      </Device>
      <Device>
        <MainDevice ZennerShortDescription="MNK-N 4-190-3/4 R80H40V CU 10L" ZennerMaterialNo="140161" WaterMeterLength="" TempRange="" SubDeviceNr="0" SerialNoFull="" Scenario="" RollerDigits="" RadioTelegramType="" RadioTechnology="" RadioProtocolMode="" PulseValue="10 Ltr/I" PrintedSerialNo="8ZRI2417429857" PermanentFlow="" PacketType="" NwkSKey="" NetworkKey="" Manufacturer="" MAC_Address="" LoRaWAN_Version="" LoRaDeviceClass="" JoinEUI="" Item="20" Frequency="" DeviceAddr="" DeviceActivationMode="" DevEUI="" Cycle="" CustomerMaterialNo="" Connection="G1B / DN 20" CommandVersion="" AppSKey="" AppKey="" AES_Key="" />
      </Device>
      <Device>
        <MainDevice ZennerShortDescription="MNK-N 4-190-3/4 R80H40V CU 10L" ZennerMaterialNo="140161" WaterMeterLength="" TempRange="" SubDeviceNr="0" SerialNoFull="" Scenario="" RollerDigits="" RadioTelegramType="" RadioTechnology="" RadioProtocolMode="" PulseValue="10 Ltr/I" PrintedSerialNo="8ZRI2417429858" PermanentFlow="" PacketType="" NwkSKey="" NetworkKey="" Manufacturer="" MAC_Address="" LoRaWAN_Version="" LoRaDeviceClass="" JoinEUI="" Item="20" Frequency="" DeviceAddr="" DeviceActivationMode="" DevEUI="" Cycle="" CustomerMaterialNo="" Connection="G1B / DN 20" CommandVersion="" AppSKey="" AppKey="" AES_Key="" />
      </Device>
      <Device>
        <MainDevice ZennerShortDescription="MNK-N 4-190-3/4 R80H40V CU 10L" ZennerMaterialNo="140161" WaterMeterLength="" TempRange="" SubDeviceNr="0" SerialNoFull="" Scenario="" RollerDigits="" RadioTelegramType="" RadioTechnology="" RadioProtocolMode="" PulseValue="10 Ltr/I" PrintedSerialNo="8ZRI2417429859" PermanentFlow="" PacketType="" NwkSKey="" NetworkKey="" Manufacturer="" MAC_Address="" LoRaWAN_Version="" LoRaDeviceClass="" JoinEUI="" Item="20" Frequency="" DeviceAddr="" DeviceActivationMode="" DevEUI="" Cycle="" CustomerMaterialNo="" Connection="G1B / DN 20" CommandVersion="" AppSKey="" AppKey="" AES_Key="" />
      </Device>
      <Device>
        <MainDevice ZennerShortDescription="MNK-N 4-190-3/4 R80H40V CU 10L" ZennerMaterialNo="140161" WaterMeterLength="" TempRange="" SubDeviceNr="0" SerialNoFull="" Scenario="" RollerDigits="" RadioTelegramType="" RadioTechnology="" RadioProtocolMode="" PulseValue="10 Ltr/I" PrintedSerialNo="8ZRI2417429860" PermanentFlow="" PacketType="" NwkSKey="" NetworkKey="" Manufacturer="" MAC_Address="" LoRaWAN_Version="" LoRaDeviceClass="" JoinEUI="" Item="20" Frequency="" DeviceAddr="" DeviceActivationMode="" DevEUI="" Cycle="" CustomerMaterialNo="" Connection="G1B / DN 20" CommandVersion="" AppSKey="" AppKey="" AES_Key="" />
      </Device>
      <Device>
        <MainDevice ZennerShortDescription="MNK-N 4-190-3/4 R80H40V CU 10L" ZennerMaterialNo="140161" WaterMeterLength="" TempRange="" SubDeviceNr="0" SerialNoFull="" Scenario="" RollerDigits="" RadioTelegramType="" RadioTechnology="" RadioProtocolMode="" PulseValue="10 Ltr/I" PrintedSerialNo="8ZRI2417429861" PermanentFlow="" PacketType="" NwkSKey="" NetworkKey="" Manufacturer="" MAC_Address="" LoRaWAN_Version="" LoRaDeviceClass="" JoinEUI="" Item="20" Frequency="" DeviceAddr="" DeviceActivationMode="" DevEUI="" Cycle="" CustomerMaterialNo="" Connection="G1B / DN 20" CommandVersion="" AppSKey="" AppKey="" AES_Key="" />
      </Device>
      <Device>
        <MainDevice ZennerShortDescription="MNK-N 4-190-3/4 R80H40V CU 10L" ZennerMaterialNo="140161" WaterMeterLength="" TempRange="" SubDeviceNr="0" SerialNoFull="" Scenario="" RollerDigits="" RadioTelegramType="" RadioTechnology="" RadioProtocolMode="" PulseValue="10 Ltr/I" PrintedSerialNo="8ZRI2417429862" PermanentFlow="" PacketType="" NwkSKey="" NetworkKey="" Manufacturer="" MAC_Address="" LoRaWAN_Version="" LoRaDeviceClass="" JoinEUI="" Item="20" Frequency="" DeviceAddr="" DeviceActivationMode="" DevEUI="" Cycle="" CustomerMaterialNo="" Connection="G1B / DN 20" CommandVersion="" AppSKey="" AppKey="" AES_Key="" />
      </Device>
      <Device>
        <MainDevice ZennerShortDescription="MNK-N 4-190-3/4 R80H40V CU 10L" ZennerMaterialNo="140161" WaterMeterLength="" TempRange="" SubDeviceNr="0" SerialNoFull="" Scenario="" RollerDigits="" RadioTelegramType="" RadioTechnology="" RadioProtocolMode="" PulseValue="10 Ltr/I" PrintedSerialNo="8ZRI2417429863" PermanentFlow="" PacketType="" NwkSKey="" NetworkKey="" Manufacturer="" MAC_Address="" LoRaWAN_Version="" LoRaDeviceClass="" JoinEUI="" Item="20" Frequency="" DeviceAddr="" DeviceActivationMode="" DevEUI="" Cycle="" CustomerMaterialNo="" Connection="G1B / DN 20" CommandVersion="" AppSKey="" AppKey="" AES_Key="" />
      </Device>
      <Device>
        <MainDevice ZennerShortDescription="MNK-N 4-190-3/4 R80H40V CU 10L" ZennerMaterialNo="140161" WaterMeterLength="" TempRange="" SubDeviceNr="0" SerialNoFull="" Scenario="" RollerDigits="" RadioTelegramType="" RadioTechnology="" RadioProtocolMode="" PulseValue="10 Ltr/I" PrintedSerialNo="8ZRI2417429864" PermanentFlow="" PacketType="" NwkSKey="" NetworkKey="" Manufacturer="" MAC_Address="" LoRaWAN_Version="" LoRaDeviceClass="" JoinEUI="" Item="20" Frequency="" DeviceAddr="" DeviceActivationMode="" DevEUI="" Cycle="" CustomerMaterialNo="" Connection="G1B / DN 20" CommandVersion="" AppSKey="" AppKey="" AES_Key="" />
      </Device>
      <Device>
        <MainDevice ZennerShortDescription="MNK-N 4-190-3/4 R80H40V CU 10L" ZennerMaterialNo="140161" WaterMeterLength="" TempRange="" SubDeviceNr="0" SerialNoFull="" Scenario="" RollerDigits="" RadioTelegramType="" RadioTechnology="" RadioProtocolMode="" PulseValue="10 Ltr/I" PrintedSerialNo="8ZRI2417429865" PermanentFlow="" PacketType="" NwkSKey="" NetworkKey="" Manufacturer="" MAC_Address="" LoRaWAN_Version="" LoRaDeviceClass="" JoinEUI="" Item="20" Frequency="" DeviceAddr="" DeviceActivationMode="" DevEUI="" Cycle="" CustomerMaterialNo="" Connection="G1B / DN 20" CommandVersion="" AppSKey="" AppKey="" AES_Key="" />
      </Device>
      <Device>
        <MainDevice ZennerShortDescription="MNK-N 4-190-3/4 R80H40V CU 10L" ZennerMaterialNo="140161" WaterMeterLength="" TempRange="" SubDeviceNr="0" SerialNoFull="" Scenario="" RollerDigits="" RadioTelegramType="" RadioTechnology="" RadioProtocolMode="" PulseValue="10 Ltr/I" PrintedSerialNo="8ZRI2417429866" PermanentFlow="" PacketType="" NwkSKey="" NetworkKey="" Manufacturer="" MAC_Address="" LoRaWAN_Version="" LoRaDeviceClass="" JoinEUI="" Item="20" Frequency="" DeviceAddr="" DeviceActivationMode="" DevEUI="" Cycle="" CustomerMaterialNo="" Connection="G1B / DN 20" CommandVersion="" AppSKey="" AppKey="" AES_Key="" />
      </Device>
      <Device>
        <MainDevice ZennerShortDescription="MNK-N 4-190-3/4 R80H40V CU 10L" ZennerMaterialNo="140161" WaterMeterLength="" TempRange="" SubDeviceNr="0" SerialNoFull="" Scenario="" RollerDigits="" RadioTelegramType="" RadioTechnology="" RadioProtocolMode="" PulseValue="10 Ltr/I" PrintedSerialNo="8ZRI2417429867" PermanentFlow="" PacketType="" NwkSKey="" NetworkKey="" Manufacturer="" MAC_Address="" LoRaWAN_Version="" LoRaDeviceClass="" JoinEUI="" Item="20" Frequency="" DeviceAddr="" DeviceActivationMode="" DevEUI="" Cycle="" CustomerMaterialNo="" Connection="G1B / DN 20" CommandVersion="" AppSKey="" AppKey="" AES_Key="" />
      </Device>
      <Device>
        <MainDevice ZennerShortDescription="MNK-N 4-190-3/4 R80H40V CU 10L" ZennerMaterialNo="140161" WaterMeterLength="" TempRange="" SubDeviceNr="0" SerialNoFull="" Scenario="" RollerDigits="" RadioTelegramType="" RadioTechnology="" RadioProtocolMode="" PulseValue="10 Ltr/I" PrintedSerialNo="8ZRI2417429868" PermanentFlow="" PacketType="" NwkSKey="" NetworkKey="" Manufacturer="" MAC_Address="" LoRaWAN_Version="" LoRaDeviceClass="" JoinEUI="" Item="20" Frequency="" DeviceAddr="" DeviceActivationMode="" DevEUI="" Cycle="" CustomerMaterialNo="" Connection="G1B / DN 20" CommandVersion="" AppSKey="" AppKey="" AES_Key="" />
      </Device>
      <Device>
        <MainDevice ZennerShortDescription="MNK-N 4-190-3/4 R80H40V CU 10L" ZennerMaterialNo="140161" WaterMeterLength="" TempRange="" SubDeviceNr="0" SerialNoFull="" Scenario="" RollerDigits="" RadioTelegramType="" RadioTechnology="" RadioProtocolMode="" PulseValue="10 Ltr/I" PrintedSerialNo="8ZRI2417429869" PermanentFlow="" PacketType="" NwkSKey="" NetworkKey="" Manufacturer="" MAC_Address="" LoRaWAN_Version="" LoRaDeviceClass="" JoinEUI="" Item="20" Frequency="" DeviceAddr="" DeviceActivationMode="" DevEUI="" Cycle="" CustomerMaterialNo="" Connection="G1B / DN 20" CommandVersion="" AppSKey="" AppKey="" AES_Key="" />
      </Device>
      <Device>
        <MainDevice ZennerShortDescription="MNK-N 4-190-3/4 R80H40V CU 10L" ZennerMaterialNo="140161" WaterMeterLength="" TempRange="" SubDeviceNr="0" SerialNoFull="" Scenario="" RollerDigits="" RadioTelegramType="" RadioTechnology="" RadioProtocolMode="" PulseValue="10 Ltr/I" PrintedSerialNo="8ZRI2417429870" PermanentFlow="" PacketType="" NwkSKey="" NetworkKey="" Manufacturer="" MAC_Address="" LoRaWAN_Version="" LoRaDeviceClass="" JoinEUI="" Item="20" Frequency="" DeviceAddr="" DeviceActivationMode="" DevEUI="" Cycle="" CustomerMaterialNo="" Connection="G1B / DN 20" CommandVersion="" AppSKey="" AppKey="" AES_Key="" />
      </Device>
      <Device>
        <MainDevice ZennerShortDescription="MNK-N 4-190-3/4 R80H40V CU 10L" ZennerMaterialNo="140161" WaterMeterLength="" TempRange="" SubDeviceNr="0" SerialNoFull="" Scenario="" RollerDigits="" RadioTelegramType="" RadioTechnology="" RadioProtocolMode="" PulseValue="10 Ltr/I" PrintedSerialNo="8ZRI2417429871" PermanentFlow="" PacketType="" NwkSKey="" NetworkKey="" Manufacturer="" MAC_Address="" LoRaWAN_Version="" LoRaDeviceClass="" JoinEUI="" Item="20" Frequency="" DeviceAddr="" DeviceActivationMode="" DevEUI="" Cycle="" CustomerMaterialNo="" Connection="G1B / DN 20" CommandVersion="" AppSKey="" AppKey="" AES_Key="" />
      </Device>
      <Device>
        <MainDevice ZennerShortDescription="MNK-N 4-190-3/4 R80H40V CU 10L" ZennerMaterialNo="140161" WaterMeterLength="" TempRange="" SubDeviceNr="0" SerialNoFull="" Scenario="" RollerDigits="" RadioTelegramType="" RadioTechnology="" RadioProtocolMode="" PulseValue="10 Ltr/I" PrintedSerialNo="8ZRI2417429872" PermanentFlow="" PacketType="" NwkSKey="" NetworkKey="" Manufacturer="" MAC_Address="" LoRaWAN_Version="" LoRaDeviceClass="" JoinEUI="" Item="20" Frequency="" DeviceAddr="" DeviceActivationMode="" DevEUI="" Cycle="" CustomerMaterialNo="" Connection="G1B / DN 20" CommandVersion="" AppSKey="" AppKey="" AES_Key="" />
      </Device>
      <Device>
        <MainDevice ZennerShortDescription="MNK-N 4-190-3/4 R80H40V CU 10L" ZennerMaterialNo="140161" WaterMeterLength="" TempRange="" SubDeviceNr="0" SerialNoFull="" Scenario="" RollerDigits="" RadioTelegramType="" RadioTechnology="" RadioProtocolMode="" PulseValue="10 Ltr/I" PrintedSerialNo="8ZRI2417429873" PermanentFlow="" PacketType="" NwkSKey="" NetworkKey="" Manufacturer="" MAC_Address="" LoRaWAN_Version="" LoRaDeviceClass="" JoinEUI="" Item="20" Frequency="" DeviceAddr="" DeviceActivationMode="" DevEUI="" Cycle="" CustomerMaterialNo="" Connection="G1B / DN 20" CommandVersion="" AppSKey="" AppKey="" AES_Key="" />
      </Device>
      <Device>
        <MainDevice ZennerShortDescription="MNK-N 4-190-3/4 R80H40V CU 10L" ZennerMaterialNo="140161" WaterMeterLength="" TempRange="" SubDeviceNr="0" SerialNoFull="" Scenario="" RollerDigits="" RadioTelegramType="" RadioTechnology="" RadioProtocolMode="" PulseValue="10 Ltr/I" PrintedSerialNo="8ZRI2417429874" PermanentFlow="" PacketType="" NwkSKey="" NetworkKey="" Manufacturer="" MAC_Address="" LoRaWAN_Version="" LoRaDeviceClass="" JoinEUI="" Item="20" Frequency="" DeviceAddr="" DeviceActivationMode="" DevEUI="" Cycle="" CustomerMaterialNo="" Connection="G1B / DN 20" CommandVersion="" AppSKey="" AppKey="" AES_Key="" />
      </Device>
      <Device>
        <MainDevice ZennerShortDescription="MNK-N 4-190-3/4 R80H40V CU 10L" ZennerMaterialNo="140161" WaterMeterLength="" TempRange="" SubDeviceNr="0" SerialNoFull="" Scenario="" RollerDigits="" RadioTelegramType="" RadioTechnology="" RadioProtocolMode="" PulseValue="10 Ltr/I" PrintedSerialNo="8ZRI2417429875" PermanentFlow="" PacketType="" NwkSKey="" NetworkKey="" Manufacturer="" MAC_Address="" LoRaWAN_Version="" LoRaDeviceClass="" JoinEUI="" Item="20" Frequency="" DeviceAddr="" DeviceActivationMode="" DevEUI="" Cycle="" CustomerMaterialNo="" Connection="G1B / DN 20" CommandVersion="" AppSKey="" AppKey="" AES_Key="" />
      </Device>
      <Device>
        <MainDevice ZennerShortDescription="MNK-N 4-190-3/4 R80H40V CU 10L" ZennerMaterialNo="140161" WaterMeterLength="" TempRange="" SubDeviceNr="0" SerialNoFull="" Scenario="" RollerDigits="" RadioTelegramType="" RadioTechnology="" RadioProtocolMode="" PulseValue="10 Ltr/I" PrintedSerialNo="8ZRI2417429876" PermanentFlow="" PacketType="" NwkSKey="" NetworkKey="" Manufacturer="" MAC_Address="" LoRaWAN_Version="" LoRaDeviceClass="" JoinEUI="" Item="20" Frequency="" DeviceAddr="" DeviceActivationMode="" DevEUI="" Cycle="" CustomerMaterialNo="" Connection="G1B / DN 20" CommandVersion="" AppSKey="" AppKey="" AES_Key="" />
      </Device>
      <Device>
        <MainDevice ZennerShortDescription="MNK-N 4-190-3/4 R80H40V CU 10L" ZennerMaterialNo="140161" WaterMeterLength="" TempRange="" SubDeviceNr="0" SerialNoFull="" Scenario="" RollerDigits="" RadioTelegramType="" RadioTechnology="" RadioProtocolMode="" PulseValue="10 Ltr/I" PrintedSerialNo="8ZRI2417429877" PermanentFlow="" PacketType="" NwkSKey="" NetworkKey="" Manufacturer="" MAC_Address="" LoRaWAN_Version="" LoRaDeviceClass="" JoinEUI="" Item="20" Frequency="" DeviceAddr="" DeviceActivationMode="" DevEUI="" Cycle="" CustomerMaterialNo="" Connection="G1B / DN 20" CommandVersion="" AppSKey="" AppKey="" AES_Key="" />
      </Device>
      <Device>
        <MainDevice ZennerShortDescription="MNK-N 4-190-3/4 R80H40V CU 10L" ZennerMaterialNo="140161" WaterMeterLength="" TempRange="" SubDeviceNr="0" SerialNoFull="" Scenario="" RollerDigits="" RadioTelegramType="" RadioTechnology="" RadioProtocolMode="" PulseValue="10 Ltr/I" PrintedSerialNo="8ZRI2417429878" PermanentFlow="" PacketType="" NwkSKey="" NetworkKey="" Manufacturer="" MAC_Address="" LoRaWAN_Version="" LoRaDeviceClass="" JoinEUI="" Item="20" Frequency="" DeviceAddr="" DeviceActivationMode="" DevEUI="" Cycle="" CustomerMaterialNo="" Connection="G1B / DN 20" CommandVersion="" AppSKey="" AppKey="" AES_Key="" />
      </Device>
      <Device>
        <MainDevice ZennerShortDescription="MNK-N 4-190-3/4 R80H40V CU 10L" ZennerMaterialNo="140161" WaterMeterLength="" TempRange="" SubDeviceNr="0" SerialNoFull="" Scenario="" RollerDigits="" RadioTelegramType="" RadioTechnology="" RadioProtocolMode="" PulseValue="10 Ltr/I" PrintedSerialNo="8ZRI2417429879" PermanentFlow="" PacketType="" NwkSKey="" NetworkKey="" Manufacturer="" MAC_Address="" LoRaWAN_Version="" LoRaDeviceClass="" JoinEUI="" Item="20" Frequency="" DeviceAddr="" DeviceActivationMode="" DevEUI="" Cycle="" CustomerMaterialNo="" Connection="G1B / DN 20" CommandVersion="" AppSKey="" AppKey="" AES_Key="" />
      </Device>
      <Device>
        <MainDevice ZennerShortDescription="MNK-N 4-190-3/4 R80H40V CU 10L" ZennerMaterialNo="140161" WaterMeterLength="" TempRange="" SubDeviceNr="0" SerialNoFull="" Scenario="" RollerDigits="" RadioTelegramType="" RadioTechnology="" RadioProtocolMode="" PulseValue="10 Ltr/I" PrintedSerialNo="8ZRI2417429880" PermanentFlow="" PacketType="" NwkSKey="" NetworkKey="" Manufacturer="" MAC_Address="" LoRaWAN_Version="" LoRaDeviceClass="" JoinEUI="" Item="20" Frequency="" DeviceAddr="" DeviceActivationMode="" DevEUI="" Cycle="" CustomerMaterialNo="" Connection="G1B / DN 20" CommandVersion="" AppSKey="" AppKey="" AES_Key="" />
      </Device>
      <Device>
        <MainDevice ZennerShortDescription="MNK-N 4-190-3/4 R80H40V CU 10L" ZennerMaterialNo="140161" WaterMeterLength="" TempRange="" SubDeviceNr="0" SerialNoFull="" Scenario="" RollerDigits="" RadioTelegramType="" RadioTechnology="" RadioProtocolMode="" PulseValue="10 Ltr/I" PrintedSerialNo="8ZRI2417429881" PermanentFlow="" PacketType="" NwkSKey="" NetworkKey="" Manufacturer="" MAC_Address="" LoRaWAN_Version="" LoRaDeviceClass="" JoinEUI="" Item="20" Frequency="" DeviceAddr="" DeviceActivationMode="" DevEUI="" Cycle="" CustomerMaterialNo="" Connection="G1B / DN 20" CommandVersion="" AppSKey="" AppKey="" AES_Key="" />
      </Device>
      <Device>
        <MainDevice ZennerShortDescription="MNK-N 4-190-3/4 R80H40V CU 10L" ZennerMaterialNo="140161" WaterMeterLength="" TempRange="" SubDeviceNr="0" SerialNoFull="" Scenario="" RollerDigits="" RadioTelegramType="" RadioTechnology="" RadioProtocolMode="" PulseValue="10 Ltr/I" PrintedSerialNo="8ZRI2417429882" PermanentFlow="" PacketType="" NwkSKey="" NetworkKey="" Manufacturer="" MAC_Address="" LoRaWAN_Version="" LoRaDeviceClass="" JoinEUI="" Item="20" Frequency="" DeviceAddr="" DeviceActivationMode="" DevEUI="" Cycle="" CustomerMaterialNo="" Connection="G1B / DN 20" CommandVersion="" AppSKey="" AppKey="" AES_Key="" />
      </Device>
      <Device>
        <MainDevice ZennerShortDescription="MNK-N 4-190-3/4 R80H40V CU 10L" ZennerMaterialNo="140161" WaterMeterLength="" TempRange="" SubDeviceNr="0" SerialNoFull="" Scenario="" RollerDigits="" RadioTelegramType="" RadioTechnology="" RadioProtocolMode="" PulseValue="10 Ltr/I" PrintedSerialNo="8ZRI2417429883" PermanentFlow="" PacketType="" NwkSKey="" NetworkKey="" Manufacturer="" MAC_Address="" LoRaWAN_Version="" LoRaDeviceClass="" JoinEUI="" Item="20" Frequency="" DeviceAddr="" DeviceActivationMode="" DevEUI="" Cycle="" CustomerMaterialNo="" Connection="G1B / DN 20" CommandVersion="" AppSKey="" AppKey="" AES_Key="" />
      </Device>
      <Device>
        <MainDevice ZennerShortDescription="MNK-N 4-190-3/4 R80H40V CU 10L" ZennerMaterialNo="140161" WaterMeterLength="" TempRange="" SubDeviceNr="0" SerialNoFull="" Scenario="" RollerDigits="" RadioTelegramType="" RadioTechnology="" RadioProtocolMode="" PulseValue="10 Ltr/I" PrintedSerialNo="8ZRI2417429884" PermanentFlow="" PacketType="" NwkSKey="" NetworkKey="" Manufacturer="" MAC_Address="" LoRaWAN_Version="" LoRaDeviceClass="" JoinEUI="" Item="20" Frequency="" DeviceAddr="" DeviceActivationMode="" DevEUI="" Cycle="" CustomerMaterialNo="" Connection="G1B / DN 20" CommandVersion="" AppSKey="" AppKey="" AES_Key="" />
      </Device>
      <Device>
        <MainDevice ZennerShortDescription="MNK-N 4-190-3/4 R80H40V CU 10L" ZennerMaterialNo="140161" WaterMeterLength="" TempRange="" SubDeviceNr="0" SerialNoFull="" Scenario="" RollerDigits="" RadioTelegramType="" RadioTechnology="" RadioProtocolMode="" PulseValue="10 Ltr/I" PrintedSerialNo="8ZRI2417429885" PermanentFlow="" PacketType="" NwkSKey="" NetworkKey="" Manufacturer="" MAC_Address="" LoRaWAN_Version="" LoRaDeviceClass="" JoinEUI="" Item="20" Frequency="" DeviceAddr="" DeviceActivationMode="" DevEUI="" Cycle="" CustomerMaterialNo="" Connection="G1B / DN 20" CommandVersion="" AppSKey="" AppKey="" AES_Key="" />
      </Device>
      <Device>
        <MainDevice ZennerShortDescription="MNK-N 4-190-3/4 R80H40V CU 10L" ZennerMaterialNo="140161" WaterMeterLength="" TempRange="" SubDeviceNr="0" SerialNoFull="" Scenario="" RollerDigits="" RadioTelegramType="" RadioTechnology="" RadioProtocolMode="" PulseValue="10 Ltr/I" PrintedSerialNo="8ZRI2417429886" PermanentFlow="" PacketType="" NwkSKey="" NetworkKey="" Manufacturer="" MAC_Address="" LoRaWAN_Version="" LoRaDeviceClass="" JoinEUI="" Item="20" Frequency="" DeviceAddr="" DeviceActivationMode="" DevEUI="" Cycle="" CustomerMaterialNo="" Connection="G1B / DN 20" CommandVersion="" AppSKey="" AppKey="" AES_Key="" />
      </Device>
      <Device>
        <MainDevice ZennerShortDescription="MNK-N 4-190-3/4 R80H40V CU 10L" ZennerMaterialNo="140161" WaterMeterLength="" TempRange="" SubDeviceNr="0" SerialNoFull="" Scenario="" RollerDigits="" RadioTelegramType="" RadioTechnology="" RadioProtocolMode="" PulseValue="10 Ltr/I" PrintedSerialNo="8ZRI2417429887" PermanentFlow="" PacketType="" NwkSKey="" NetworkKey="" Manufacturer="" MAC_Address="" LoRaWAN_Version="" LoRaDeviceClass="" JoinEUI="" Item="20" Frequency="" DeviceAddr="" DeviceActivationMode="" DevEUI="" Cycle="" CustomerMaterialNo="" Connection="G1B / DN 20" CommandVersion="" AppSKey="" AppKey="" AES_Key="" />
      </Device>
      <Device>
        <MainDevice ZennerShortDescription="MNK-N 4-190-3/4 R80H40V CU 10L" ZennerMaterialNo="140161" WaterMeterLength="" TempRange="" SubDeviceNr="0" SerialNoFull="" Scenario="" RollerDigits="" RadioTelegramType="" RadioTechnology="" RadioProtocolMode="" PulseValue="10 Ltr/I" PrintedSerialNo="8ZRI2417429888" PermanentFlow="" PacketType="" NwkSKey="" NetworkKey="" Manufacturer="" MAC_Address="" LoRaWAN_Version="" LoRaDeviceClass="" JoinEUI="" Item="20" Frequency="" DeviceAddr="" DeviceActivationMode="" DevEUI="" Cycle="" CustomerMaterialNo="" Connection="G1B / DN 20" CommandVersion="" AppSKey="" AppKey="" AES_Key="" />
      </Device>
      <Device>
        <MainDevice ZennerShortDescription="MNK-N 4-190-3/4 R80H40V CU 10L" ZennerMaterialNo="140161" WaterMeterLength="" TempRange="" SubDeviceNr="0" SerialNoFull="" Scenario="" RollerDigits="" RadioTelegramType="" RadioTechnology="" RadioProtocolMode="" PulseValue="10 Ltr/I" PrintedSerialNo="8ZRI2417429889" PermanentFlow="" PacketType="" NwkSKey="" NetworkKey="" Manufacturer="" MAC_Address="" LoRaWAN_Version="" LoRaDeviceClass="" JoinEUI="" Item="20" Frequency="" DeviceAddr="" DeviceActivationMode="" DevEUI="" Cycle="" CustomerMaterialNo="" Connection="G1B / DN 20" CommandVersion="" AppSKey="" AppKey="" AES_Key="" />
      </Device>
      <Device>
        <MainDevice ZennerShortDescription="MNK-N 4-190-3/4 R80H40V CU 10L" ZennerMaterialNo="140161" WaterMeterLength="" TempRange="" SubDeviceNr="0" SerialNoFull="" Scenario="" RollerDigits="" RadioTelegramType="" RadioTechnology="" RadioProtocolMode="" PulseValue="10 Ltr/I" PrintedSerialNo="8ZRI2417429890" PermanentFlow="" PacketType="" NwkSKey="" NetworkKey="" Manufacturer="" MAC_Address="" LoRaWAN_Version="" LoRaDeviceClass="" JoinEUI="" Item="20" Frequency="" DeviceAddr="" DeviceActivationMode="" DevEUI="" Cycle="" CustomerMaterialNo="" Connection="G1B / DN 20" CommandVersion="" AppSKey="" AppKey="" AES_Key="" />
      </Device>
      <Device>
        <MainDevice ZennerShortDescription="MNK-N 4-190-3/4 R80H40V CU 10L" ZennerMaterialNo="140161" WaterMeterLength="" TempRange="" SubDeviceNr="0" SerialNoFull="" Scenario="" RollerDigits="" RadioTelegramType="" RadioTechnology="" RadioProtocolMode="" PulseValue="10 Ltr/I" PrintedSerialNo="8ZRI2417429891" PermanentFlow="" PacketType="" NwkSKey="" NetworkKey="" Manufacturer="" MAC_Address="" LoRaWAN_Version="" LoRaDeviceClass="" JoinEUI="" Item="20" Frequency="" DeviceAddr="" DeviceActivationMode="" DevEUI="" Cycle="" CustomerMaterialNo="" Connection="G1B / DN 20" CommandVersion="" AppSKey="" AppKey="" AES_Key="" />
      </Device>
      <Device>
        <MainDevice ZennerShortDescription="MNK-N 4-190-3/4 R80H40V CU 10L" ZennerMaterialNo="140161" WaterMeterLength="" TempRange="" SubDeviceNr="0" SerialNoFull="" Scenario="" RollerDigits="" RadioTelegramType="" RadioTechnology="" RadioProtocolMode="" PulseValue="10 Ltr/I" PrintedSerialNo="8ZRI2417429892" PermanentFlow="" PacketType="" NwkSKey="" NetworkKey="" Manufacturer="" MAC_Address="" LoRaWAN_Version="" LoRaDeviceClass="" JoinEUI="" Item="20" Frequency="" DeviceAddr="" DeviceActivationMode="" DevEUI="" Cycle="" CustomerMaterialNo="" Connection="G1B / DN 20" CommandVersion="" AppSKey="" AppKey="" AES_Key="" />
      </Device>
      <Device>
        <MainDevice ZennerShortDescription="MNK-N 4-190-3/4 R80H40V CU 10L" ZennerMaterialNo="140161" WaterMeterLength="" TempRange="" SubDeviceNr="0" SerialNoFull="" Scenario="" RollerDigits="" RadioTelegramType="" RadioTechnology="" RadioProtocolMode="" PulseValue="10 Ltr/I" PrintedSerialNo="8ZRI2417429893" PermanentFlow="" PacketType="" NwkSKey="" NetworkKey="" Manufacturer="" MAC_Address="" LoRaWAN_Version="" LoRaDeviceClass="" JoinEUI="" Item="20" Frequency="" DeviceAddr="" DeviceActivationMode="" DevEUI="" Cycle="" CustomerMaterialNo="" Connection="G1B / DN 20" CommandVersion="" AppSKey="" AppKey="" AES_Key="" />
      </Device>
      <Device>
        <MainDevice ZennerShortDescription="MNK-N 4-190-3/4 R80H40V CU 10L" ZennerMaterialNo="140161" WaterMeterLength="" TempRange="" SubDeviceNr="0" SerialNoFull="" Scenario="" RollerDigits="" RadioTelegramType="" RadioTechnology="" RadioProtocolMode="" PulseValue="10 Ltr/I" PrintedSerialNo="8ZRI2417429894" PermanentFlow="" PacketType="" NwkSKey="" NetworkKey="" Manufacturer="" MAC_Address="" LoRaWAN_Version="" LoRaDeviceClass="" JoinEUI="" Item="20" Frequency="" DeviceAddr="" DeviceActivationMode="" DevEUI="" Cycle="" CustomerMaterialNo="" Connection="G1B / DN 20" CommandVersion="" AppSKey="" AppKey="" AES_Key="" />
      </Device>
      <Device>
        <MainDevice ZennerShortDescription="MNK-N 4-190-3/4 R80H40V CU 10L" ZennerMaterialNo="140161" WaterMeterLength="" TempRange="" SubDeviceNr="0" SerialNoFull="" Scenario="" RollerDigits="" RadioTelegramType="" RadioTechnology="" RadioProtocolMode="" PulseValue="10 Ltr/I" PrintedSerialNo="8ZRI2417429895" PermanentFlow="" PacketType="" NwkSKey="" NetworkKey="" Manufacturer="" MAC_Address="" LoRaWAN_Version="" LoRaDeviceClass="" JoinEUI="" Item="20" Frequency="" DeviceAddr="" DeviceActivationMode="" DevEUI="" Cycle="" CustomerMaterialNo="" Connection="G1B / DN 20" CommandVersion="" AppSKey="" AppKey="" AES_Key="" />
      </Device>
      <Device>
        <MainDevice ZennerShortDescription="MNK-N 4-190-3/4 R80H40V CU 10L" ZennerMaterialNo="140161" WaterMeterLength="" TempRange="" SubDeviceNr="0" SerialNoFull="" Scenario="" RollerDigits="" RadioTelegramType="" RadioTechnology="" RadioProtocolMode="" PulseValue="10 Ltr/I" PrintedSerialNo="8ZRI2417429896" PermanentFlow="" PacketType="" NwkSKey="" NetworkKey="" Manufacturer="" MAC_Address="" LoRaWAN_Version="" LoRaDeviceClass="" JoinEUI="" Item="20" Frequency="" DeviceAddr="" DeviceActivationMode="" DevEUI="" Cycle="" CustomerMaterialNo="" Connection="G1B / DN 20" CommandVersion="" AppSKey="" AppKey="" AES_Key="" />
      </Device>
      <Device>
        <MainDevice ZennerShortDescription="MNK-N 4-190-3/4 R80H40V CU 10L" ZennerMaterialNo="140161" WaterMeterLength="" TempRange="" SubDeviceNr="0" SerialNoFull="" Scenario="" RollerDigits="" RadioTelegramType="" RadioTechnology="" RadioProtocolMode="" PulseValue="10 Ltr/I" PrintedSerialNo="8ZRI2417429897" PermanentFlow="" PacketType="" NwkSKey="" NetworkKey="" Manufacturer="" MAC_Address="" LoRaWAN_Version="" LoRaDeviceClass="" JoinEUI="" Item="20" Frequency="" DeviceAddr="" DeviceActivationMode="" DevEUI="" Cycle="" CustomerMaterialNo="" Connection="G1B / DN 20" CommandVersion="" AppSKey="" AppKey="" AES_Key="" />
      </Device>
      <Device>
        <MainDevice ZennerShortDescription="MNK-N 4-190-3/4 R80H40V CU 10L" ZennerMaterialNo="140161" WaterMeterLength="" TempRange="" SubDeviceNr="0" SerialNoFull="" Scenario="" RollerDigits="" RadioTelegramType="" RadioTechnology="" RadioProtocolMode="" PulseValue="10 Ltr/I" PrintedSerialNo="8ZRI2417429898" PermanentFlow="" PacketType="" NwkSKey="" NetworkKey="" Manufacturer="" MAC_Address="" LoRaWAN_Version="" LoRaDeviceClass="" JoinEUI="" Item="20" Frequency="" DeviceAddr="" DeviceActivationMode="" DevEUI="" Cycle="" CustomerMaterialNo="" Connection="G1B / DN 20" CommandVersion="" AppSKey="" AppKey="" AES_Key="" />
      </Device>
      <Device>
        <MainDevice ZennerShortDescription="MNK-N 4-190-3/4 R80H40V CU 10L" ZennerMaterialNo="140161" WaterMeterLength="" TempRange="" SubDeviceNr="0" SerialNoFull="" Scenario="" RollerDigits="" RadioTelegramType="" RadioTechnology="" RadioProtocolMode="" PulseValue="10 Ltr/I" PrintedSerialNo="8ZRI2417429899" PermanentFlow="" PacketType="" NwkSKey="" NetworkKey="" Manufacturer="" MAC_Address="" LoRaWAN_Version="" LoRaDeviceClass="" JoinEUI="" Item="20" Frequency="" DeviceAddr="" DeviceActivationMode="" DevEUI="" Cycle="" CustomerMaterialNo="" Connection="G1B / DN 20" CommandVersion="" AppSKey="" AppKey="" AES_Key="" />
      </Device>
      <Device>
        <MainDevice ZennerShortDescription="MNK-N 4-190-3/4 R80H40V CU 10L" ZennerMaterialNo="140161" WaterMeterLength="" TempRange="" SubDeviceNr="0" SerialNoFull="" Scenario="" RollerDigits="" RadioTelegramType="" RadioTechnology="" RadioProtocolMode="" PulseValue="10 Ltr/I" PrintedSerialNo="8ZRI2417429900" PermanentFlow="" PacketType="" NwkSKey="" NetworkKey="" Manufacturer="" MAC_Address="" LoRaWAN_Version="" LoRaDeviceClass="" JoinEUI="" Item="20" Frequency="" DeviceAddr="" DeviceActivationMode="" DevEUI="" Cycle="" CustomerMaterialNo="" Connection="G1B / DN 20" CommandVersion="" AppSKey="" AppKey="" AES_Key="" />
      </Device>
      <Device>
        <MainDevice ZennerShortDescription="MNK-N 4-190-3/4 R80H40V CU 10L" ZennerMaterialNo="140161" WaterMeterLength="" TempRange="" SubDeviceNr="0" SerialNoFull="" Scenario="" RollerDigits="" RadioTelegramType="" RadioTechnology="" RadioProtocolMode="" PulseValue="10 Ltr/I" PrintedSerialNo="8ZRI2417429901" PermanentFlow="" PacketType="" NwkSKey="" NetworkKey="" Manufacturer="" MAC_Address="" LoRaWAN_Version="" LoRaDeviceClass="" JoinEUI="" Item="20" Frequency="" DeviceAddr="" DeviceActivationMode="" DevEUI="" Cycle="" CustomerMaterialNo="" Connection="G1B / DN 20" CommandVersion="" AppSKey="" AppKey="" AES_Key="" />
      </Device>
      <Device>
        <MainDevice ZennerShortDescription="MNK-N 4-190-3/4 R80H40V CU 10L" ZennerMaterialNo="140161" WaterMeterLength="" TempRange="" SubDeviceNr="0" SerialNoFull="" Scenario="" RollerDigits="" RadioTelegramType="" RadioTechnology="" RadioProtocolMode="" PulseValue="10 Ltr/I" PrintedSerialNo="8ZRI2417429902" PermanentFlow="" PacketType="" NwkSKey="" NetworkKey="" Manufacturer="" MAC_Address="" LoRaWAN_Version="" LoRaDeviceClass="" JoinEUI="" Item="20" Frequency="" DeviceAddr="" DeviceActivationMode="" DevEUI="" Cycle="" CustomerMaterialNo="" Connection="G1B / DN 20" CommandVersion="" AppSKey="" AppKey="" AES_Key="" />
      </Device>
      <Device>
        <MainDevice ZennerShortDescription="MNK-N 4-190-3/4 R80H40V CU 10L" ZennerMaterialNo="140161" WaterMeterLength="" TempRange="" SubDeviceNr="0" SerialNoFull="" Scenario="" RollerDigits="" RadioTelegramType="" RadioTechnology="" RadioProtocolMode="" PulseValue="10 Ltr/I" PrintedSerialNo="8ZRI2417429903" PermanentFlow="" PacketType="" NwkSKey="" NetworkKey="" Manufacturer="" MAC_Address="" LoRaWAN_Version="" LoRaDeviceClass="" JoinEUI="" Item="20" Frequency="" DeviceAddr="" DeviceActivationMode="" DevEUI="" Cycle="" CustomerMaterialNo="" Connection="G1B / DN 20" CommandVersion="" AppSKey="" AppKey="" AES_Key="" />
      </Device>
      <Device>
        <MainDevice ZennerShortDescription="MNK-N 4-190-3/4 R80H40V CU 10L" ZennerMaterialNo="140161" WaterMeterLength="" TempRange="" SubDeviceNr="0" SerialNoFull="" Scenario="" RollerDigits="" RadioTelegramType="" RadioTechnology="" RadioProtocolMode="" PulseValue="10 Ltr/I" PrintedSerialNo="8ZRI2417429904" PermanentFlow="" PacketType="" NwkSKey="" NetworkKey="" Manufacturer="" MAC_Address="" LoRaWAN_Version="" LoRaDeviceClass="" JoinEUI="" Item="20" Frequency="" DeviceAddr="" DeviceActivationMode="" DevEUI="" Cycle="" CustomerMaterialNo="" Connection="G1B / DN 20" CommandVersion="" AppSKey="" AppKey="" AES_Key="" />
      </Device>
      <Device>
        <MainDevice ZennerShortDescription="MNK-N 4-190-3/4 R80H40V CU 10L" ZennerMaterialNo="140161" WaterMeterLength="" TempRange="" SubDeviceNr="0" SerialNoFull="" Scenario="" RollerDigits="" RadioTelegramType="" RadioTechnology="" RadioProtocolMode="" PulseValue="10 Ltr/I" PrintedSerialNo="8ZRI2417429905" PermanentFlow="" PacketType="" NwkSKey="" NetworkKey="" Manufacturer="" MAC_Address="" LoRaWAN_Version="" LoRaDeviceClass="" JoinEUI="" Item="20" Frequency="" DeviceAddr="" DeviceActivationMode="" DevEUI="" Cycle="" CustomerMaterialNo="" Connection="G1B / DN 20" CommandVersion="" AppSKey="" AppKey="" AES_Key="" />
      </Device>
      <Device>
        <MainDevice ZennerShortDescription="MNK-N 4-190-3/4 R80H40V CU 10L" ZennerMaterialNo="140161" WaterMeterLength="" TempRange="" SubDeviceNr="0" SerialNoFull="" Scenario="" RollerDigits="" RadioTelegramType="" RadioTechnology="" RadioProtocolMode="" PulseValue="10 Ltr/I" PrintedSerialNo="8ZRI2417429906" PermanentFlow="" PacketType="" NwkSKey="" NetworkKey="" Manufacturer="" MAC_Address="" LoRaWAN_Version="" LoRaDeviceClass="" JoinEUI="" Item="20" Frequency="" DeviceAddr="" DeviceActivationMode="" DevEUI="" Cycle="" CustomerMaterialNo="" Connection="G1B / DN 20" CommandVersion="" AppSKey="" AppKey="" AES_Key="" />
      </Device>
      <Device>
        <MainDevice ZennerShortDescription="MNK-N 4-190-3/4 R80H40V CU 10L" ZennerMaterialNo="140161" WaterMeterLength="" TempRange="" SubDeviceNr="0" SerialNoFull="" Scenario="" RollerDigits="" RadioTelegramType="" RadioTechnology="" RadioProtocolMode="" PulseValue="10 Ltr/I" PrintedSerialNo="8ZRI2417429907" PermanentFlow="" PacketType="" NwkSKey="" NetworkKey="" Manufacturer="" MAC_Address="" LoRaWAN_Version="" LoRaDeviceClass="" JoinEUI="" Item="20" Frequency="" DeviceAddr="" DeviceActivationMode="" DevEUI="" Cycle="" CustomerMaterialNo="" Connection="G1B / DN 20" CommandVersion="" AppSKey="" AppKey="" AES_Key="" />
      </Device>
      <Device>
        <MainDevice ZennerShortDescription="MNK-N 4-190-3/4 R80H40V CU 10L" ZennerMaterialNo="140161" WaterMeterLength="" TempRange="" SubDeviceNr="0" SerialNoFull="" Scenario="" RollerDigits="" RadioTelegramType="" RadioTechnology="" RadioProtocolMode="" PulseValue="10 Ltr/I" PrintedSerialNo="8ZRI2417429908" PermanentFlow="" PacketType="" NwkSKey="" NetworkKey="" Manufacturer="" MAC_Address="" LoRaWAN_Version="" LoRaDeviceClass="" JoinEUI="" Item="20" Frequency="" DeviceAddr="" DeviceActivationMode="" DevEUI="" Cycle="" CustomerMaterialNo="" Connection="G1B / DN 20" CommandVersion="" AppSKey="" AppKey="" AES_Key="" />
      </Device>
      <Device>
        <MainDevice ZennerShortDescription="MNK-N 4-190-3/4 R80H40V CU 10L" ZennerMaterialNo="140161" WaterMeterLength="" TempRange="" SubDeviceNr="0" SerialNoFull="" Scenario="" RollerDigits="" RadioTelegramType="" RadioTechnology="" RadioProtocolMode="" PulseValue="10 Ltr/I" PrintedSerialNo="8ZRI2417429909" PermanentFlow="" PacketType="" NwkSKey="" NetworkKey="" Manufacturer="" MAC_Address="" LoRaWAN_Version="" LoRaDeviceClass="" JoinEUI="" Item="20" Frequency="" DeviceAddr="" DeviceActivationMode="" DevEUI="" Cycle="" CustomerMaterialNo="" Connection="G1B / DN 20" CommandVersion="" AppSKey="" AppKey="" AES_Key="" />
      </Device>
      <Device>
        <MainDevice ZennerShortDescription="MNK-N 4-190-3/4 R80H40V CU 10L" ZennerMaterialNo="140161" WaterMeterLength="" TempRange="" SubDeviceNr="0" SerialNoFull="" Scenario="" RollerDigits="" RadioTelegramType="" RadioTechnology="" RadioProtocolMode="" PulseValue="10 Ltr/I" PrintedSerialNo="8ZRI2417429910" PermanentFlow="" PacketType="" NwkSKey="" NetworkKey="" Manufacturer="" MAC_Address="" LoRaWAN_Version="" LoRaDeviceClass="" JoinEUI="" Item="20" Frequency="" DeviceAddr="" DeviceActivationMode="" DevEUI="" Cycle="" CustomerMaterialNo="" Connection="G1B / DN 20" CommandVersion="" AppSKey="" AppKey="" AES_Key="" />
      </Device>
      <Device>
        <MainDevice ZennerShortDescription="MNK-N 4-190-3/4 R80H40V CU 10L" ZennerMaterialNo="140161" WaterMeterLength="" TempRange="" SubDeviceNr="0" SerialNoFull="" Scenario="" RollerDigits="" RadioTelegramType="" RadioTechnology="" RadioProtocolMode="" PulseValue="10 Ltr/I" PrintedSerialNo="8ZRI2417429911" PermanentFlow="" PacketType="" NwkSKey="" NetworkKey="" Manufacturer="" MAC_Address="" LoRaWAN_Version="" LoRaDeviceClass="" JoinEUI="" Item="20" Frequency="" DeviceAddr="" DeviceActivationMode="" DevEUI="" Cycle="" CustomerMaterialNo="" Connection="G1B / DN 20" CommandVersion="" AppSKey="" AppKey="" AES_Key="" />
      </Device>
      <Device>
        <MainDevice ZennerShortDescription="MNK-N 4-190-3/4 R80H40V CU 10L" ZennerMaterialNo="140161" WaterMeterLength="" TempRange="" SubDeviceNr="0" SerialNoFull="" Scenario="" RollerDigits="" RadioTelegramType="" RadioTechnology="" RadioProtocolMode="" PulseValue="10 Ltr/I" PrintedSerialNo="8ZRI2417429912" PermanentFlow="" PacketType="" NwkSKey="" NetworkKey="" Manufacturer="" MAC_Address="" LoRaWAN_Version="" LoRaDeviceClass="" JoinEUI="" Item="20" Frequency="" DeviceAddr="" DeviceActivationMode="" DevEUI="" Cycle="" CustomerMaterialNo="" Connection="G1B / DN 20" CommandVersion="" AppSKey="" AppKey="" AES_Key="" />
      </Device>
      <Device>
        <MainDevice ZennerShortDescription="MNK-N 4-190-3/4 R80H40V CU 10L" ZennerMaterialNo="140161" WaterMeterLength="" TempRange="" SubDeviceNr="0" SerialNoFull="" Scenario="" RollerDigits="" RadioTelegramType="" RadioTechnology="" RadioProtocolMode="" PulseValue="10 Ltr/I" PrintedSerialNo="8ZRI2417429913" PermanentFlow="" PacketType="" NwkSKey="" NetworkKey="" Manufacturer="" MAC_Address="" LoRaWAN_Version="" LoRaDeviceClass="" JoinEUI="" Item="20" Frequency="" DeviceAddr="" DeviceActivationMode="" DevEUI="" Cycle="" CustomerMaterialNo="" Connection="G1B / DN 20" CommandVersion="" AppSKey="" AppKey="" AES_Key="" />
      </Device>
      <Device>
        <MainDevice ZennerShortDescription="MNK-N 4-190-3/4 R80H40V CU 10L" ZennerMaterialNo="140161" WaterMeterLength="" TempRange="" SubDeviceNr="0" SerialNoFull="" Scenario="" RollerDigits="" RadioTelegramType="" RadioTechnology="" RadioProtocolMode="" PulseValue="10 Ltr/I" PrintedSerialNo="8ZRI2417429914" PermanentFlow="" PacketType="" NwkSKey="" NetworkKey="" Manufacturer="" MAC_Address="" LoRaWAN_Version="" LoRaDeviceClass="" JoinEUI="" Item="20" Frequency="" DeviceAddr="" DeviceActivationMode="" DevEUI="" Cycle="" CustomerMaterialNo="" Connection="G1B / DN 20" CommandVersion="" AppSKey="" AppKey="" AES_Key="" />
      </Device>
      <Device>
        <MainDevice ZennerShortDescription="MNK-N 4-190-3/4 R80H40V CU 10L" ZennerMaterialNo="140161" WaterMeterLength="" TempRange="" SubDeviceNr="0" SerialNoFull="" Scenario="" RollerDigits="" RadioTelegramType="" RadioTechnology="" RadioProtocolMode="" PulseValue="10 Ltr/I" PrintedSerialNo="8ZRI2417429915" PermanentFlow="" PacketType="" NwkSKey="" NetworkKey="" Manufacturer="" MAC_Address="" LoRaWAN_Version="" LoRaDeviceClass="" JoinEUI="" Item="20" Frequency="" DeviceAddr="" DeviceActivationMode="" DevEUI="" Cycle="" CustomerMaterialNo="" Connection="G1B / DN 20" CommandVersion="" AppSKey="" AppKey="" AES_Key="" />
      </Device>
      <Device>
        <MainDevice ZennerShortDescription="MNK-N 4-190-3/4 R80H40V CU 10L" ZennerMaterialNo="140161" WaterMeterLength="" TempRange="" SubDeviceNr="0" SerialNoFull="" Scenario="" RollerDigits="" RadioTelegramType="" RadioTechnology="" RadioProtocolMode="" PulseValue="10 Ltr/I" PrintedSerialNo="8ZRI2417429916" PermanentFlow="" PacketType="" NwkSKey="" NetworkKey="" Manufacturer="" MAC_Address="" LoRaWAN_Version="" LoRaDeviceClass="" JoinEUI="" Item="20" Frequency="" DeviceAddr="" DeviceActivationMode="" DevEUI="" Cycle="" CustomerMaterialNo="" Connection="G1B / DN 20" CommandVersion="" AppSKey="" AppKey="" AES_Key="" />
      </Device>
      <Device>
        <MainDevice ZennerShortDescription="MNK-N 4-190-3/4 R80H40V CU 10L" ZennerMaterialNo="140161" WaterMeterLength="" TempRange="" SubDeviceNr="0" SerialNoFull="" Scenario="" RollerDigits="" RadioTelegramType="" RadioTechnology="" RadioProtocolMode="" PulseValue="10 Ltr/I" PrintedSerialNo="8ZRI2417429917" PermanentFlow="" PacketType="" NwkSKey="" NetworkKey="" Manufacturer="" MAC_Address="" LoRaWAN_Version="" LoRaDeviceClass="" JoinEUI="" Item="20" Frequency="" DeviceAddr="" DeviceActivationMode="" DevEUI="" Cycle="" CustomerMaterialNo="" Connection="G1B / DN 20" CommandVersion="" AppSKey="" AppKey="" AES_Key="" />
      </Device>
      <Device>
        <MainDevice ZennerShortDescription="MNK-N 4-190-3/4 R80H40V CU 10L" ZennerMaterialNo="140161" WaterMeterLength="" TempRange="" SubDeviceNr="0" SerialNoFull="" Scenario="" RollerDigits="" RadioTelegramType="" RadioTechnology="" RadioProtocolMode="" PulseValue="10 Ltr/I" PrintedSerialNo="8ZRI2417429918" PermanentFlow="" PacketType="" NwkSKey="" NetworkKey="" Manufacturer="" MAC_Address="" LoRaWAN_Version="" LoRaDeviceClass="" JoinEUI="" Item="20" Frequency="" DeviceAddr="" DeviceActivationMode="" DevEUI="" Cycle="" CustomerMaterialNo="" Connection="G1B / DN 20" CommandVersion="" AppSKey="" AppKey="" AES_Key="" />
      </Device>
      <Device>
        <MainDevice ZennerShortDescription="MNK-N 4-190-3/4 R80H40V CU 10L" ZennerMaterialNo="140161" WaterMeterLength="" TempRange="" SubDeviceNr="0" SerialNoFull="" Scenario="" RollerDigits="" RadioTelegramType="" RadioTechnology="" RadioProtocolMode="" PulseValue="10 Ltr/I" PrintedSerialNo="8ZRI2417429919" PermanentFlow="" PacketType="" NwkSKey="" NetworkKey="" Manufacturer="" MAC_Address="" LoRaWAN_Version="" LoRaDeviceClass="" JoinEUI="" Item="20" Frequency="" DeviceAddr="" DeviceActivationMode="" DevEUI="" Cycle="" CustomerMaterialNo="" Connection="G1B / DN 20" CommandVersion="" AppSKey="" AppKey="" AES_Key="" />
      </Device>
      <Device>
        <MainDevice ZennerShortDescription="MNK-N 4-190-3/4 R80H40V CU 10L" ZennerMaterialNo="140161" WaterMeterLength="" TempRange="" SubDeviceNr="0" SerialNoFull="" Scenario="" RollerDigits="" RadioTelegramType="" RadioTechnology="" RadioProtocolMode="" PulseValue="10 Ltr/I" PrintedSerialNo="8ZRI2417429920" PermanentFlow="" PacketType="" NwkSKey="" NetworkKey="" Manufacturer="" MAC_Address="" LoRaWAN_Version="" LoRaDeviceClass="" JoinEUI="" Item="20" Frequency="" DeviceAddr="" DeviceActivationMode="" DevEUI="" Cycle="" CustomerMaterialNo="" Connection="G1B / DN 20" CommandVersion="" AppSKey="" AppKey="" AES_Key="" />
      </Device>
      <Device>
        <MainDevice ZennerShortDescription="MNK-N 4-190-3/4 R80H40V CU 10L" ZennerMaterialNo="140161" WaterMeterLength="" TempRange="" SubDeviceNr="0" SerialNoFull="" Scenario="" RollerDigits="" RadioTelegramType="" RadioTechnology="" RadioProtocolMode="" PulseValue="10 Ltr/I" PrintedSerialNo="8ZRI2417429921" PermanentFlow="" PacketType="" NwkSKey="" NetworkKey="" Manufacturer="" MAC_Address="" LoRaWAN_Version="" LoRaDeviceClass="" JoinEUI="" Item="20" Frequency="" DeviceAddr="" DeviceActivationMode="" DevEUI="" Cycle="" CustomerMaterialNo="" Connection="G1B / DN 20" CommandVersion="" AppSKey="" AppKey="" AES_Key="" />
      </Device>
      <Device>
        <MainDevice ZennerShortDescription="MNK-N 4-190-3/4 R80H40V CU 10L" ZennerMaterialNo="140161" WaterMeterLength="" TempRange="" SubDeviceNr="0" SerialNoFull="" Scenario="" RollerDigits="" RadioTelegramType="" RadioTechnology="" RadioProtocolMode="" PulseValue="10 Ltr/I" PrintedSerialNo="8ZRI2417429922" PermanentFlow="" PacketType="" NwkSKey="" NetworkKey="" Manufacturer="" MAC_Address="" LoRaWAN_Version="" LoRaDeviceClass="" JoinEUI="" Item="20" Frequency="" DeviceAddr="" DeviceActivationMode="" DevEUI="" Cycle="" CustomerMaterialNo="" Connection="G1B / DN 20" CommandVersion="" AppSKey="" AppKey="" AES_Key="" />
      </Device>
      <Device>
        <MainDevice ZennerShortDescription="MNK-N 4-190-3/4 R80H40V CU 10L" ZennerMaterialNo="140161" WaterMeterLength="" TempRange="" SubDeviceNr="0" SerialNoFull="" Scenario="" RollerDigits="" RadioTelegramType="" RadioTechnology="" RadioProtocolMode="" PulseValue="10 Ltr/I" PrintedSerialNo="8ZRI2417429923" PermanentFlow="" PacketType="" NwkSKey="" NetworkKey="" Manufacturer="" MAC_Address="" LoRaWAN_Version="" LoRaDeviceClass="" JoinEUI="" Item="20" Frequency="" DeviceAddr="" DeviceActivationMode="" DevEUI="" Cycle="" CustomerMaterialNo="" Connection="G1B / DN 20" CommandVersion="" AppSKey="" AppKey="" AES_Key="" />
      </Device>
      <Device>
        <MainDevice ZennerShortDescription="MNK-N 4-190-3/4 R80H40V CU 10L" ZennerMaterialNo="140161" WaterMeterLength="" TempRange="" SubDeviceNr="0" SerialNoFull="" Scenario="" RollerDigits="" RadioTelegramType="" RadioTechnology="" RadioProtocolMode="" PulseValue="10 Ltr/I" PrintedSerialNo="8ZRI2417429924" PermanentFlow="" PacketType="" NwkSKey="" NetworkKey="" Manufacturer="" MAC_Address="" LoRaWAN_Version="" LoRaDeviceClass="" JoinEUI="" Item="20" Frequency="" DeviceAddr="" DeviceActivationMode="" DevEUI="" Cycle="" CustomerMaterialNo="" Connection="G1B / DN 20" CommandVersion="" AppSKey="" AppKey="" AES_Key="" />
      </Device>
      <Device>
        <MainDevice ZennerShortDescription="MNK-N 4-190-3/4 R80H40V CU 10L" ZennerMaterialNo="140161" WaterMeterLength="" TempRange="" SubDeviceNr="0" SerialNoFull="" Scenario="" RollerDigits="" RadioTelegramType="" RadioTechnology="" RadioProtocolMode="" PulseValue="10 Ltr/I" PrintedSerialNo="8ZRI2417429925" PermanentFlow="" PacketType="" NwkSKey="" NetworkKey="" Manufacturer="" MAC_Address="" LoRaWAN_Version="" LoRaDeviceClass="" JoinEUI="" Item="20" Frequency="" DeviceAddr="" DeviceActivationMode="" DevEUI="" Cycle="" CustomerMaterialNo="" Connection="G1B / DN 20" CommandVersion="" AppSKey="" AppKey="" AES_Key="" />
      </Device>
      <Device>
        <MainDevice ZennerShortDescription="MNK-N 4-190-3/4 R80H40V CU 10L" ZennerMaterialNo="140161" WaterMeterLength="" TempRange="" SubDeviceNr="0" SerialNoFull="" Scenario="" RollerDigits="" RadioTelegramType="" RadioTechnology="" RadioProtocolMode="" PulseValue="10 Ltr/I" PrintedSerialNo="8ZRI2417429926" PermanentFlow="" PacketType="" NwkSKey="" NetworkKey="" Manufacturer="" MAC_Address="" LoRaWAN_Version="" LoRaDeviceClass="" JoinEUI="" Item="20" Frequency="" DeviceAddr="" DeviceActivationMode="" DevEUI="" Cycle="" CustomerMaterialNo="" Connection="G1B / DN 20" CommandVersion="" AppSKey="" AppKey="" AES_Key="" />
      </Device>
      <Device>
        <MainDevice ZennerShortDescription="MNK-N 4-190-3/4 R80H40V CU 10L" ZennerMaterialNo="140161" WaterMeterLength="" TempRange="" SubDeviceNr="0" SerialNoFull="" Scenario="" RollerDigits="" RadioTelegramType="" RadioTechnology="" RadioProtocolMode="" PulseValue="10 Ltr/I" PrintedSerialNo="8ZRI2417429927" PermanentFlow="" PacketType="" NwkSKey="" NetworkKey="" Manufacturer="" MAC_Address="" LoRaWAN_Version="" LoRaDeviceClass="" JoinEUI="" Item="20" Frequency="" DeviceAddr="" DeviceActivationMode="" DevEUI="" Cycle="" CustomerMaterialNo="" Connection="G1B / DN 20" CommandVersion="" AppSKey="" AppKey="" AES_Key="" />
      </Device>
      <Device>
        <MainDevice ZennerShortDescription="MNK-N 4-190-3/4 R80H40V CU 10L" ZennerMaterialNo="140161" WaterMeterLength="" TempRange="" SubDeviceNr="0" SerialNoFull="" Scenario="" RollerDigits="" RadioTelegramType="" RadioTechnology="" RadioProtocolMode="" PulseValue="10 Ltr/I" PrintedSerialNo="8ZRI2417429928" PermanentFlow="" PacketType="" NwkSKey="" NetworkKey="" Manufacturer="" MAC_Address="" LoRaWAN_Version="" LoRaDeviceClass="" JoinEUI="" Item="20" Frequency="" DeviceAddr="" DeviceActivationMode="" DevEUI="" Cycle="" CustomerMaterialNo="" Connection="G1B / DN 20" CommandVersion="" AppSKey="" AppKey="" AES_Key="" />
      </Device>
      <Device>
        <MainDevice ZennerShortDescription="MNK-N 4-190-3/4 R80H40V CU 10L" ZennerMaterialNo="140161" WaterMeterLength="" TempRange="" SubDeviceNr="0" SerialNoFull="" Scenario="" RollerDigits="" RadioTelegramType="" RadioTechnology="" RadioProtocolMode="" PulseValue="10 Ltr/I" PrintedSerialNo="8ZRI2417429929" PermanentFlow="" PacketType="" NwkSKey="" NetworkKey="" Manufacturer="" MAC_Address="" LoRaWAN_Version="" LoRaDeviceClass="" JoinEUI="" Item="20" Frequency="" DeviceAddr="" DeviceActivationMode="" DevEUI="" Cycle="" CustomerMaterialNo="" Connection="G1B / DN 20" CommandVersion="" AppSKey="" AppKey="" AES_Key="" />
      </Device>
      <Device>
        <MainDevice ZennerShortDescription="MNK-N 4-190-3/4 R80H40V CU 10L" ZennerMaterialNo="140161" WaterMeterLength="" TempRange="" SubDeviceNr="0" SerialNoFull="" Scenario="" RollerDigits="" RadioTelegramType="" RadioTechnology="" RadioProtocolMode="" PulseValue="10 Ltr/I" PrintedSerialNo="8ZRI2417429930" PermanentFlow="" PacketType="" NwkSKey="" NetworkKey="" Manufacturer="" MAC_Address="" LoRaWAN_Version="" LoRaDeviceClass="" JoinEUI="" Item="20" Frequency="" DeviceAddr="" DeviceActivationMode="" DevEUI="" Cycle="" CustomerMaterialNo="" Connection="G1B / DN 20" CommandVersion="" AppSKey="" AppKey="" AES_Key="" />
      </Device>
      <Device>
        <MainDevice ZennerShortDescription="MNK-N 4-190-3/4 R80H40V CU 10L" ZennerMaterialNo="140161" WaterMeterLength="" TempRange="" SubDeviceNr="0" SerialNoFull="" Scenario="" RollerDigits="" RadioTelegramType="" RadioTechnology="" RadioProtocolMode="" PulseValue="10 Ltr/I" PrintedSerialNo="8ZRI2417429931" PermanentFlow="" PacketType="" NwkSKey="" NetworkKey="" Manufacturer="" MAC_Address="" LoRaWAN_Version="" LoRaDeviceClass="" JoinEUI="" Item="20" Frequency="" DeviceAddr="" DeviceActivationMode="" DevEUI="" Cycle="" CustomerMaterialNo="" Connection="G1B / DN 20" CommandVersion="" AppSKey="" AppKey="" AES_Key="" />
      </Device>
      <Device>
        <MainDevice ZennerShortDescription="MNK-N 4-190-3/4 R80H40V CU 10L" ZennerMaterialNo="140161" WaterMeterLength="" TempRange="" SubDeviceNr="0" SerialNoFull="" Scenario="" RollerDigits="" RadioTelegramType="" RadioTechnology="" RadioProtocolMode="" PulseValue="10 Ltr/I" PrintedSerialNo="8ZRI2417429932" PermanentFlow="" PacketType="" NwkSKey="" NetworkKey="" Manufacturer="" MAC_Address="" LoRaWAN_Version="" LoRaDeviceClass="" JoinEUI="" Item="20" Frequency="" DeviceAddr="" DeviceActivationMode="" DevEUI="" Cycle="" CustomerMaterialNo="" Connection="G1B / DN 20" CommandVersion="" AppSKey="" AppKey="" AES_Key="" />
      </Device>
    </Devices>
  </DeliveryNote>
</DeliveryNotes>